Workbook

Sheet Leia primeiro
A1: Inventário das fontes de dados da Nekt — tarefa #1747
A2: Posição de 21/10/2026 (refaz o inventário de 16/10). Escopo: planilha oficial de contas de 16/10, sem mudança. Medido hoje: gasto da Meta (13–19/10, 286 contas relidas), gasto da Nekt no Google (13/09–12/10), linhas e último dado de Meta, Google e RD, varredura de fontes e suítes de qualidade. NÃO refeito hoje: a referência de gasto do Google na plataforma (MCC de 16/10; a ferramenta de consulta não estava conectada), o gasto em dólar e euro, e a leitura das 48 fontes novas de Instagram e Páginas. Somente leitura.
A4: RESULTADO
A5: Cobertura real: 159 de 209 contas aplicáveis com leitura confirmada (76,1%); 130 com dado ativo (62,2%); 161 conectadas (77,0%).
A6: Cobertura por gasto: Meta 64,5% (13–19/10, reais); Google 97,1% (30 dias, reais, sem a Nova Era e sem os ex-clientes e inativos; com eles no denominador o número é menor, ver aba Cobertura).
A7: Saneamento da base: 1.483 de 1.485 regras de qualidade conformes (99,9%; 37 suítes; 1 alerta e 1 bloqueante, explicados no relatório). É outra medida: não diz nada sobre contas que ainda não chegaram.
A9: DEFINIÇÕES (as cinco medidas)
A10: Saneamento da base: Quanto do dado que JÁ chegou passa nos testes de qualidade (tipos, duplicidade, fuso, integridade). → 1.483 de 1.485 regras conformes (99,9%) nas 37 suítes, lidas em 21/10. | Limite: Não diz nada sobre contas que ainda não chegaram. É por isso que 99,9% de saneamento convive com cobertura de leitura de 76%.
A11: Conectada: A fonte está publicada na Nekt e a última execução terminou com sucesso. → 161 de 209 contas (77,0%). | Limite: Sucesso de execução não prova dado: há fontes com sucesso e zero linhas.
A12: Leitura confirmada: Conectada E o que a Nekt leu bate com a plataforma (Meta e Google) ou há dado presente (RD). → 159 de 209 contas (76,1%). | Limite: Inclui contas sem veiculação, cuja leitura correta é zero. No RD não existe referência independente: vale "dado presente".
A13: Dado ativo: Leitura confirmada E dado recente (Meta até 30/09, Google até 28/09, RD até 15/09). → 130 de 209 contas (62,2%). | Limite: É o piso: a visão mais exigente.
A14: Cobertura por gasto: Quanto do investimento da plataforma está em contas que a Nekt lê. → Meta 64,5% (7 dias); Google 97,1% (30 dias, sem Nova Era, ex-clientes e inativos). | Limite: É a medida que mais pesa para o negócio. Só vale para Meta e Google em reais.
... A25: 5. Autorizar o arquivamento, na interface da Nekt (o MCP não arquiva), das fontes duplicadas de RD (1eaJ e bjQx) e das fontes dos ex-clientes ainda publicadas.

Sheet Contas
A1: Plataforma | B1: Cliente | C1: ID da conta | D1: Nome na plataforma | E1: Fonte na Nekt | F1: Estado | G1: Linhas medidas (Nekt) | H1: Último dado | I1: Medido na Nekt (janela; no RD = nº de conversões) | J1: Medido na plataforma (janela) | K1: Diferença Nekt − plataforma | L1: Moeda | M1: Janela | N1: Impedimento | O1: Responsável (a confirmar) | P1: Prioridade | Q1: Etapa | R1: Previsão (proposta) | S1: Observação
A2: Google Ads | B2: ACESSO SAÚDE | C2: 175-244-3056 | D2: ACESSO SAÚDE | E2: google-ads-cwt3 | F2: 1 Funcional — dado ativo | G2: 6018 | H2: 2026-10-19 | I2: 2207.23 | J2: 2207.23 | K2: 0 | L2: BRL | M2: gasto 13/09-12/10 | O2: Administrador do MCC Google Ads 170-443-9246 (a confirmar) | Q2: E1 reautorizar conector v2.53 ate 23/10 | R2: 2026-10-23
A3: Google Ads | B3: AMZ GERADORES | C3: 339-788-6954 | D3: AMZ Geradores | E3: google-ads-ZcMG | F3: 1 Funcional — dado ativo | G3: 633 | H3: 2026-10-19 | I3: 1640.45 | J3: 1640.45 | K3: 0 | L3: BRL | M3: gasto 13/09-12/10 | O3: Administrador do MCC Google Ads 170-443-9246 (a confirmar) | Q3: E1 reautorizar conector v2.53 ate 23/10 | R3: 2026-10-23
A4: Google Ads | B4: ARENA TINTAS | C4: 315-247-9850 | D4: Arena Tintas | E4: google-ads-x36N | F4: 1 Funcional — dado ativo | G4: 2379 | H4: 2026-10-19 | I4: 3553.33 | J4: 3553.33 | K4: 0 | L4: BRL | M4: gasto 13/09-12/10 | O4: Administrador do MCC Google Ads 170-443-9246 (a confirmar) | Q4: E1 reautorizar conector v2.53 ate 23/10 | R4: 2026-10-23
A5: Google Ads | B5: BA ELÉTRICA | C5: 374-652-9772 | D5: CA - BA Elétrica | E5: google-ads-WxA8 | F5: 1 Funcional — dado ativo | G5: 1798 | H5: 2026-10-19 | I5: 1574.34 | J5: 1574.34 | K5: 0 | L5: BRL | M5: gasto 13/09-12/10 | O5: Administrador do MCC Google Ads 170-443-9246 (a confirmar) | Q5: E1 reautorizar conector v2.53 ate 23/10 | R5: 2026-10-23
A6: Google Ads | B6: BIGAZINE | C6: 249-409-3513 | D6: Bigazine | E6: google-ads-dMx7 | F6: 1 Funcional — dado ativo | G6: 1688 | H6: 2026-10-19 | I6: 3004.85 | J6: 3004.85 | K6: 0 | L6: BRL | M6: gasto 13/09-12/10 | O6: Administrador do MCC Google Ads 170-443-9246 (a confirmar) | Q6: E1 reautorizar conector v2.53 ate 23/10 | R6: 2026-10-23
A7: Google Ads | B7: BRAGA ACESSÓRIOS | C7: 319-374-7131 | D7: Braga Acessórios | E7: google-ads-6Z2v | F7: 1 Funcional — dado ativo | G7: 1863 | H7: 2026-10-19 | I7: 1962.88 | J7: 1962.88 | K7: 0 | L7: BRL | M7: gasto 13/09-12/10 | O7: Nekt (Jussara) | Q7: E1 reautorizar conector v2.53 ate 23/10 | R7: 2026-10-20
A8: Google Ads | B8: BRAGA MINI | C8: 876-663-8384 | D8: BRAGA MOTORS - MINI | E8: google-ads-RCRU | F8: 1 Funcional — dado ativo | G8: 1152 | H8: 2026-10-19 | I8: 265.73 | J8: 265.73 | K8: 0 | L8: BRL | M8: gasto 13/09-12/10 | O8: Nekt (Jussara) | Q8: E1 reautorizar conector v2.53 ate 23/10 | R8: 2026-10-20
A9: Google Ads | B9: BRAGA MOTORRAD | MOTO BMW | C9: 660-489-2813 | D9: BRAGA MOTORS - MOTORRAD | E9: google-ads-VozJ | F9: 1 Funcional — dado ativo | G9: 1018 | H9: 2026-10-19 | I9: 105.54 | J9: 105.54 | K9: 0 | L9: BRL | M9: gasto 13/09-12/10 | O9: Nekt (Jussara) | Q9: E1 reautorizar conector v2.53 ate 23/10 | R9: 2026-10-20
A10: Google Ads | B10: BRAGA MOTORS BMW | C10: 935-985-8042 | D10: BRAGA VEICULOS LTDA | E10: google-ads-cFrH | F10: 1 Funcional — dado ativo | G10: 3053 | H10: 2026-10-19 | I10: 1503.13 | J10: 1503.91 | K10: -0.78 | L10: BRL | M10: gasto 13/09-12/10 | O10: Nekt (Jussara) | Q10: E1 reautorizar conector v2.53 ate 23/10 | R10: 2026-10-20
A11: Google Ads | B11: BRAGA YAMAHA | C11: 187-499-5593 | D11: Braga Motos | E11: google-ads-Pk69 | F11: 1 Funcional — dado ativo | G11: 4170 | H11: 2026-10-19 | I11: 925.58 | J11: 925.58 | K11: 0 | L11: BRL | M11: gasto 13/09-12/10 | O11: Nekt (Jussara) | Q11: E1 reautorizar conector v2.53 ate 23/10 | R11: 2026-10-20
A12: Google Ads | B12: BRAGA YAMAHA CONSÓRCIOS | C12: 421-608-6233 | D12: Braga Consórcio | E12: google-ads-5J1y | F12: 1 Funcional — dado ativo | G12: 4839 | H12: 2026-10-19 | I12: 2316.64 | J12: 2316.64 | K12: 0 | L12: BRL | M12: gasto 13/09-12/10 | O12: Nekt (Jussara) | Q12: E1 reautorizar conector v2.53 ate 23/10 | R12: 2026-10-20
A13: Google Ads | B13: CAA ALUMÍNIO | C13: 938-204-4362 | D13: CAA - ALUMINIO | E13: google-ads-A1kM | F13: 1 Funcional — dado ativo | G13: 1159 | H13: 2026-10-19 | I13: 821.54 | J13: 821.54 | K13: 0 | L13: BRL | M13: gasto 13/09-12/10 | O13: Administrador do MCC Google Ads 170-443-9246 (a confirmar) | Q13: E1 reautorizar conector v2.53 ate 23/10 | R13: 2026-10-23
... A25: Google Ads | B25: PNEU FORTE DISTRIBUIDORA | C25: 666-695-8748 | D25: Pneu Forte | Distribuidora | E25: google-ads-0B2k | F25: 1 Funcional — dado ativo | G25: 467 | H25: 2026-10-19 | I25: 1223.08 | J25: 1223.08 | K25: 0 | L25: BRL | M25: gasto 13/09-12/10 | O25: Administrador do MCC Google Ads 170-443-9246 (a confirmar) | Q25: E1 reautorizar conector v2.53 ate 23/10 | R25: 2026-10-23
A26: Google Ads | B26: PRESTEX | C26: 712-071-7819 | D26: Prestex | E26: google-ads-OzfZ | F26: 1 Funcional — dado ativo | G26: 827 | H26: 2026-10-12 | J26: 11285.82 | L26: BRL | M26: gasto 13/09-12/10 | O26: Administrador do MCC Google Ads 170-443-9246 (a confirmar) | Q26: E1 reautorizar conector v2.53 ate 23/10 | R26: 2026-10-21
A27: Google Ads | B27: REI DAS MANGUEIRAS | C27: 958-037-9854 | D27: Rei das Mangueiras | E27: google-ads-PnyV | F27: 1 Funcional — dado ativo | G27: 656 | H27: 2026-10-19 | I27: 834.05 | J27: 834.05 | K27: 0 | L27: BRL | M27: gasto 13/09-12/10 | O27: Administrador do MCC Google Ads 170-443-9246 (a confirmar) | Q27: E1 reautorizar conector v2.53 ate 23/10 | R27: 2026-10-23
A28: Google Ads | B28: RODRIX | C28: 973-940-7801 | D28: RODRIX MOTOS | E28: google-ads-rYKp | F28: 1 Funcional — dado ativo | G28: 34 | H28: 2026-10-19 | I28: 2492.6 | J28: 2492.6 | K28: 0 | L28: BRL | M28: gasto 13/09-12/10 | O28: Administrador do MCC Google Ads 170-443-9246 (a confirmar) | Q28: E1 reautorizar conector v2.53 ate 23/10 | R28: 2026-10-23
A29: Google Ads | B29: ROYAL ENFIELD | C29: 121-447-4505 | D29: ROYAL ENFIELD | E29: google-ads-SyTu | F29: 1 Funcional — dado ativo | G29: 2817 | H29: 2026-10-19 | I29: 1246.57 | J29: 1246.57 | K29: 0 | L29: BRL | M29: gasto 13/09-12/10 | O29: Nekt (Jussara) | Q29: E1 reautorizar conector v2.53 ate 23/10 | R29: 2026-10-20
A30: Google Ads | B30: SMILE PNEUS | C30: 139-590-6460 | D30: Pneu Forte l Smile Pneus | E30: google-ads-Jl1R | F30: 1 Funcional — dado ativo | G30: 8 | H30: 2026-10-19 | I30: 0 | J30: 0 | K30: 0 | L30: BRL | M30: gasto 13/09-12/10 | O30: Administrador do MCC Google Ads 170-443-9246 (a confirmar) | Q30: E1 reautorizar conector v2.53 ate 23/10 | R30: 2026-10-23
A31: Google Ads | B31: UNIPAR | C31: 191-198-4217 | D31: Parque das Torres | E31: google-ads-hBlk | F31: 1 Funcional — dado ativo | G31: 1231 | H31: 2026-10-19 | I31: 2369.66 | M31: gasto 13/09-12/10 | O31: Nekt (Jussara) | Q31: E1 reautorizar conector v2.53 ate 23/10 | R31: 2026-10-20
A32: Google Ads | B32: UNIPAR | C32: 645-156-8997 | D32: Neo Vila | E32: google-ads-mvUx | F32: 1 Funcional — dado ativo | G32: 1040 | H32: 2026-10-19 | I32: 1005.49 | M32: gasto 13/09-12/10 | O32: Nekt (Jussara) | Q32: E1 reautorizar conector v2.53 ate 23/10 | R32: 2026-10-20
A33: Google Ads | B33: UNIPAR | C33: 308-342-8472 | D33: Boa Vista | E33: google-ads-3eFc | F33: 1 Funcional — dado ativo | G33: 946 | H33: 2026-10-19 | I33: 1217.4 | M33: gasto 13/09-12/10 | O33: Nekt (Jussara) | Q33: E1 reautorizar conector v2.53 ate 23/10 | R33: 2026-10-20
A34: Google Ads | B34: AMAZONCOPY | C34: 888-702-2182 | D34: Amazoncopy | E34: google-ads-fwxw | F34: 2 Funcional — conta parada (leitura confirmada) | G34: 378 | H34: 2025-11-26 | I34: 0 | J34: 0 | K34: 0 | L34: BRL | M34: gasto 13/09-12/10 | O34: Administrador do MCC Google Ads 170-443-9246 (a confirmar) | Q34: E1 reautorizar conector v2.53 ate 23/10 | R34: 2026-10-23
A35: Google Ads | B35: BRAGA PÓS VENDAS | C35: 180-732-5368 | D35: BRAGA VEÍCULOS PÓS VENDAS | E35: google-ads-PsES | F35: 2 Funcional — conta parada (leitura confirmada) | G35: 1656 | H35: 2026-07-23 | I35: 0 | J35: 0 | K35: 0 | L35: BRL | M35: gasto 13/09-12/10 | O35: Nekt (Jussara) | Q35: E1 reautorizar conector v2.53 ate 23/10 | R35: 2026-10-20
A36: Google Ads | B36: BRAGA VAREJO | C36: 843-763-2791 | D36: Braga Motomarcas | E36: google-ads-PmFB | F36: 2 Funcional — conta parada (leitura confirmada) | G36: 1109 | H36: 2025-08-30 | I36: 0 | J36: 0 | K36: 0 | L36: BRL | M36: gasto 13/09-12/10 | O36: Nekt (Jussara) | Q36: E1 reautorizar conector v2.53 ate 23/10 | R36: 2026-10-20
A37: Google Ads | B37: DEB TRANSPORTADORA | C37: 403-235-5891 | D37: DEB Transportes | E37: google-ads-C4Aq | F37: 2 Funcional — conta parada (leitura confirmada) | G37: 68 | H37: 2026-10-01 | I37: 0 | J37: 0 | K37: 0 | L37: BRL | M37: gasto 13/09-12/10 | O37: Administrador do MCC Google Ads 170-443-9246 (a confirmar) | Q37: E1 reautorizar conector v2.53 ate 23/10 | R37: 2026-10-23
A38: Google Ads | B38: DMELLO (TEMPO DAS TINTAS) | C38: 331-057-9239 | D38: Dmello Tempo das Tintas | E38: google-ads-URNQ | F38: 2 Funcional — conta parada (leitura confirmada) | G38: 87 | H38: 2026-08-24 | I38: 0 | J38: 0 | K38: 0 | L38: BRL | M38: gasto 13/09-12/10 | O38: Admin do MCC (reautorizacao v2.53) | Q38: E1 reautorizar conector v2.53 ate 23/10 | R38: 2026-10-23 | S38: Linha acrescentada em 15/10: a fonte existia e nao constava da planilha.
A39: Google Ads | B39: DON WATCHES (conta 1) | C39: 855-373-3895 | D39: Don Watches - Ativa | E39: google-ads-vE2C | F39: 2 Funcional — conta parada (leitura confirmada) | G39: 0 | J39: 0 | L39: BRL | M39: gasto 13/09-12/10 | O39: AM (Silvia Calderaro) | Q39: E1 reautorizar conector v2.53 ate 23/10 | S39: Candidata a encerrar (validar com AM)
A40: Google Ads | B40: DON WATCHES (conta 2) | C40: 945-172-6644 | D40: Don Watches - Ativa Validada | E40: google-ads-QuKh | F40: 2 Funcional — conta parada (leitura confirmada) | G40: 107 | H40: 2026-08-22 | I40: 0 | J40: 0 | K40: 0 | L40: BRL | M40: gasto 13/09-12/10 | O40: Administrador do MCC Google Ads 170-443-9246 (a confirmar) | Q40: E1 reautorizar conector v2.53 ate 23/10 | R40: 2026-10-23
A41: Google Ads | B41: DR. CABRAL (conta 1) | C41: 738-192-0209 | D41: Dr. Cabral | E41: google-ads-wypN | F41: 2 Funcional — conta parada (leitura confirmada) | G41: 0 | J41: 0 | L41: BRL | M41: gasto 13/09-12/10 | O41: Administrador do MCC Google Ads 170-443-9246 (a confirmar) | Q41: E1 reautorizar conector v2.53 ate 23/10 | R41: 2026-10-21 | S41: Candidata a encerrar (validar com AM)
A42: Google Ads | B42: STEEL PORT | C42: 987-090-1843 | D42: Steel Port Am | E42: google-ads-x20o | F42: 2 Funcional — conta parada (leitura confirmada) | G42: 42 | H42: 2026-03-27 | I42: 0 | J42: 0 | K42: 0 | L42: BRL | M42: gasto 13/09-12/10 | O42: Administrador do MCC Google Ads 170-443-9246 (a confirmar) | Q42: E1 reautorizar conector v2.53 ate 23/10 | R42: 2026-10-23
A43: Google Ads | B43: AÇO MANAUS | C43: 514-135-8700 | D43: Aço Manaus | E43: google-ads-DhJv | F43: 4 Pendente | J43: 1366.26 | L43: BRL | M43: gasto 13/09-12/10 | N43: Conta sem fonte na Nekt hoje | O43: Account Manager (confirmar se a conta ainda é cliente) | P43: P1 | Q43: E2 publicar rascunho | R43: 2026-10-21
A44: Google Ads | B44: BRAGA MOTORS BMW | C44: 432-609-6939 | D44: BRAGA MOTORS - CARRO | E44: google-ads-H4oR | F44: 4 Pendente | J44: 27.39 | L44: BRL | M44: gasto 13/09-12/10 | N44: Conta sem fonte na Nekt hoje | O44: Account Manager (confirmar se a conta ainda é cliente) | P44: P2 | Q44: E2 publicar rascunho | R44: 2026-10-21
A45: Google Ads | B45: PNEU FORTE VAREJO | C45: 399-828-7431 | D45: Pneu Forte | Varejo | E45: google-ads-H3hJ | F45: 4 Pendente | J45: 768.29 | L45: BRL | M45: gasto 13/09-12/10 | N45: OAuth com usuário Google que administra o MCC | O45: Administrador do MCC Google Ads 170-443-9246 (a confirmar) | P45: P2 | Q45: E2 publicar rascunho | R45: 2026-10-21
A46: Google Ads | B46: TUBOAÇOS DA AMAZÔNIA | C46: 752-297-1952 | D46: Tuboaços Da Amazônia | E46: google-ads-1pe8 | F46: 4 Pendente | J46: 174.46 | L46: BRL | M46: gasto 13/09-12/10 | N46: Conta sem fonte na Nekt hoje | O46: Account Manager (confirmar se a conta ainda é cliente) | P46: P2 | Q46: E2 publicar rascunho | R46: 2026-10-21
A47: Google Ads | B47: VANGUARDA COMUNICAÇÃO (conta própria) | C47: 750-265-3880 | D47: Vanguarda | F47: 4 Pendente | J47: 161.26 | L47: BRL | M47: gasto 13/09-12/10 | N47: Conta propria da agencia com gasto e sem fonte; decidir se entra (a Meta da Vanguarda ja entra) | O47: Admin do MCC / Jussara | P47: P2 | Q47: E2 publicar rascunho | R47: 2026-10-23 | S47: Linha acrescentada em 15/10 apos cruzar as 85 contas do MCC.
A48: Google Ads | B48: BRAGA VENDA DIRETA | C48: 580-542-7544 | D48: Braga venda direta | E48: — | F48: 5 Bloqueada | M48: gasto 13/09-12/10 | N48: Conta não vinculada ao MCC da Vanguarda ou ID divergente | O48: João (confirmar ID) + Administrador do MCC Google Ads 170-443-9246 (a confirmar) | P48: P2 | Q48: E1 desbloquear | R48: 2026-10-21
A49: Google Ads | B49: CDL MANAUS | C49: 661-855-7333 | D49: Cdl Manaus | E49: google-ads-zksL | F49: 5 Bloqueada | J49: 536.96 | L49: BRL | M49: gasto 13/09-12/10 | N49: Conta sem fonte na Nekt hoje | O49: Account Manager (confirmar se a conta ainda é cliente) | P49: P2 | Q49: E1 desbloquear | R49: 2026-10-21
A50: Google Ads | B50: COMAC | C50: 306-130-0045 | D50: Comac | E50: — | F50: 5 Bloqueada | M50: gasto 13/09-12/10 | N50: Conta não vinculada ao MCC da Vanguarda ou ID divergente | O50: João (confirmar ID) + Administrador do MCC Google Ads 170-443-9246 (a confirmar) | P50: P2 | Q50: E1 desbloquear | R50: 2026-10-21
A51: Google Ads | B51: SANTO REMÉDIO | C51: 281-904-4460 | D51: SANTO REMÉDIO VNG | E51: google-ads-AMd2 | F51: 5 Bloqueada | G51: 280 | H51: 2025-07-16 | I51: 0 | M51: gasto 13/09-12/10 | N51: Conta viva do Santo Remédio é outra (513-801-6841, rascunho z1CZ) | O51: Administrador do MCC Google Ads 170-443-9246 (a confirmar) | P51: P2 | Q51: E1 desbloquear | R51: 2026-10-21
A52: Google Ads | B52: LOJA | NOVA ERA BV | PIX | C52: 867-580-5325 | D52: LOJA | NOVA ERA BV | PIX | E52: — | F52: 6 Fora do escopo (Nova Era) | J52: 1487.11 | L52: BRL | M52: gasto 13/09-12/10 | N52: Conta segue vinculada ao MCC da Vanguarda | O52: Jussara + administrador do MCC | Q52: fora do escopo | R52: 2026-10-23
A53: Google Ads | B53: LOJA | NOVA ERA PVH | PIX | C53: 967-327-5366 | D53: LOJA | NOVA ERA PVH | PIX | E53: — | F53: 6 Fora do escopo (Nova Era) | J53: 3404.76 | L53: BRL | M53: gasto 13/09-12/10 | N53: Conta segue vinculada ao MCC da Vanguarda | O53: Jussara + administrador do MCC | Q53: fora do escopo | R53: 2026-10-23
A54: Google Ads | B54: NOVA ERA MAO | LOJAS | C54: 267-561-1013 | D54: NOVA ERA MAO | LOJAS | E54: — | F54: 6 Fora do escopo (Nova Era) | J54: 10422.25 | L54: BRL | M54: gasto 13/09-12/10 | N54: Conta segue vinculada ao MCC da Vanguarda | O54: Jussara + administrador do MCC | Q54: fora do escopo | R54: 2026-10-23
A55: Google Ads | B55: NOVA ERA | MANAUS | ECOMM | C55: 446-964-3023 | D55: NOVA ERA | MANAUS | ECOMM | E55: — | F55: 6 Fora do escopo (Nova Era) | J55: 9187.33 | L55: BRL | M55: gasto 13/09-12/10 | N55: Conta segue vinculada ao MCC da Vanguarda | O55: Jussara + administrador do MCC | Q55: fora do escopo | R55: 2026-10-23
A56: Google Ads | B56: NOVA ERA | PORTO VELHO | ECOMM | C56: 669-397-8711 | D56: NOVA ERA | PORTO VELHO | ECOMM | E56: — | F56: 6 Fora do escopo (Nova Era) | J56: 1989.24 | L56: BRL | M56: gasto 13/09-12/10 | N56: Conta segue vinculada ao MCC da Vanguarda | O56: Jussara + administrador do MCC | Q56: fora do escopo | R56: 2026-10-23
A57: Google Ads | B57: DR. CABRAL (conta 2 NOVA) | C57: 251-691-8741 | D57: Dr. Cabral [NOVA] | E57: google-ads-4YJU | F57: 8 Dispensável (duplicata, ex-cliente, inativo, duplicidade ou decisão de não conectar) | J57: 1930.04 | L57: BRL | M57: gasto 13/09-12/10 | N57: Não precisa manter (duplicidade) (informado em 16/10; ver planilha oficial #1743) | O57: Account Manager (confirmar se a conta ainda é cliente) | Q57: dispensavel | R57: 2026-10-21
A58: Google Ads | B58: HOPE BAY PARK | C58: 407-149-9349 | D58: Hope Bay Park | E58: google-ads-DR7n | F58: 8 Dispensável (duplicata, ex-cliente, inativo, duplicidade ou decisão de não conectar) | J58: 1506.28 | L58: BRL | M58: gasto 13/09-12/10 | N58: Não precisa manter (ex-cliente) (informado em 16/10; ver planilha oficial #1743) | O58: Account Manager (confirmar se a conta ainda é cliente) | Q58: dispensavel | R58: 2026-10-21
A59: Google Ads | B59: JULIA HERRERA | C59: 382-053-1237 | D59: Julia Herrera | E59: google-ads-10KI | F59: 8 Dispensável (duplicata, ex-cliente, inativo, duplicidade ou decisão de não conectar) | J59: 637.19 | L59: BRL | M59: gasto 13/09-12/10 | N59: Não precisa manter (ex-cliente) (informado em 16/10; ver planilha oficial #1743) | O59: Account Manager (confirmar se a conta ainda é cliente) | Q59: dispensavel | R59: 2026-10-21
A60: Google Ads | B60: OLÁ CASA NOVA | C60: 615-504-3001 | D60: Olá Empreendimentos | E60: google-ads-DzVL | F60: 8 Dispensável (duplicata, ex-cliente, inativo, duplicidade ou decisão de não conectar) | G60: 1099 | H60: 2026-10-19 | I60: 2208.42 | J60: 2208.42 | K60: 0 | L60: BRL | M60: gasto 13/09-12/10 | N60: Não precisa manter (ex-cliente) (informado em 16/10; ver planilha oficial #1743) | O60: Administrador do MCC Google Ads 170-443-9246 (a confirmar) | Q60: dispensavel | R60: 2026-10-23
A61: Google Ads | B61: PÁTIO GOURMET (E-COM) | C61: 681-914-4625 | D61: Pátio Gourmet (E-Com) | E61: google-ads-hLZl | F61: 8 Dispensável (duplicata, ex-cliente, inativo, duplicidade ou decisão de não conectar) | J61: 3028.41 | L61: BRL | M61: gasto 13/09-12/10 | N61: Não precisa manter (ex-cliente) (informado em 16/10; ver planilha oficial #1743) | O61: Account Manager (confirmar se a conta ainda é cliente) | Q61: dispensavel | R61: 2026-10-21
A62: Google Ads | B62: PÁTIO GOURMET (LOJA) | C62: 965-772-4454 | D62: Pátio Gourmet (Loja) | E62: google-ads-4aNo | F62: 8 Dispensável (duplicata, ex-cliente, inativo, duplicidade ou decisão de não conectar) | J62: 13.66 | L62: BRL | M62: gasto 13/09-12/10 | N62: Não precisa manter (ex-cliente) (informado em 16/10; ver planilha oficial #1743) | O62: Account Manager (confirmar se a conta ainda é cliente) | Q62: dispensavel | R62: 2026-10-21
A63: Google Ads | B63: SANTO REMÉDIO (conta viva) | C63: 513-801-6841 | D63: Santo Remédio (Conta Viva) | E63: google-ads-z1CZ | F63: 8 Dispensável (duplicata, ex-cliente, inativo, duplicidade ou decisão de não conectar) | J63: 3545.39 | L63: BRL | M63: gasto 13/09-12/10 | N63: Não precisa manter (decisão: não conectar por ora) (informado em 16/10; ver planilha oficial #1743) | O63: Account Manager (confirmar se a conta ainda é cliente) | Q63: dispensavel | R63: 2026-10-21
A64: Google Ads | B64: UIARA AMAZON RESORT | C64: 193-832-6229 | D64: Uiara Amazon Resort | E64: google-ads-WKmK | F64: 8 Dispensável (duplicata, ex-cliente, inativo, duplicidade ou decisão de não conectar) | J64: 12545.38 | L64: BRL | M64: gasto 13/09-12/10 | N64: Não precisa manter (ex-cliente) (informado em 16/10; ver planilha oficial #1743) | O64: Account Manager (confirmar se a conta ainda é cliente) | Q64: dispensavel | R64: 2026-10-21
A65: LinkedIn Ads | B65: ALMEIDA E BARRETO | C65: — | D65: conta não informada nos documentos | E65: — | F65: 7 Sem conexão | N65: ID da conta não consta em nenhum documento | O65: Analista da conta | P65: P3 | Q65: E4 levantar ID e decidir escopo | R65: 2026-10-30
A66: LinkedIn Ads | B66: AMAZONCOPY | C66: — | D66: conta não informada nos documentos | E66: — | F66: 7 Sem conexão | N66: ID da conta não consta em nenhum documento | O66: Analista da conta | P66: P3 | Q66: E4 levantar ID e decidir escopo | R66: 2026-10-30
A67: LinkedIn Ads | B67: PRESTEX | C67: — | D67: conta não informada nos documentos | E67: — | F67: 7 Sem conexão | N67: ID da conta não consta em nenhum documento | O67: Analista da conta | P67: P3 | Q67: E4 levantar ID e decidir escopo | R67: 2026-10-30
A68: LinkedIn Ads | B68: TUBOAÇOS | C68: — | D68: conta não informada nos documentos | E68: — | F68: 7 Sem conexão | N68: ID da conta não consta em nenhum documento | O68: Analista da conta | P68: P3 | Q68: E4 levantar ID e decidir escopo | R68: 2026-10-30
A69: Meta Ads | B69: ACESSO SAÚDE | C69: 261401095311098 | D69: Acesso Saúde | E69: facebook-ads-Si4U | F69: 1 Funcional — dado ativo | G69: 21713 | H69: 2026-10-20 | I69: 2124.82 | J69: 2126.15 | K69: -1.33 | L69: BRL | M69: gasto 13-19/10 | O69: — | Q69: ja na Trusted
A70: Meta Ads | B70: AMAZONCOPY | C70: 233965209271674 | D70: Amazoncopy | E70: facebook-ads-aghZ | F70: 1 Funcional — dado ativo | G70: 4286 | H70: 2026-10-20 | I70: 399.89 | J70: 400.06 | K70: -0.17 | L70: BRL | M70: gasto 13-19/10 | O70: Nekt (Jussara) | Q70: E3 somar a Trusted de Facebook (apos 20/10) | R70: 2026-10-21
A71: Meta Ads | B71: AMZ GERADORES | C71: 747929494239769 | D71: AMZ GERADORES | E71: facebook-ads-nCGL | F71: 1 Funcional — dado ativo | G71: 817 | H71: 2026-10-20 | I71: 823.59 | J71: 824.09 | K71: -0.5 | L71: BRL | M71: gasto 13-19/10 | O71: Nekt (Jussara) | Q71: E3 somar a Trusted de Facebook (apos 20/10) | R71: 2026-10-21
A72: Meta Ads | B72: ANIMATIV | C72: 202711331653880 | D72: Animativ | E72: facebook-ads-TAqE | F72: 1 Funcional — dado ativo | G72: 1217 | H72: 2026-10-20 | I72: 104.65 | J72: 104.65 | K72: 0 | L72: BRL | M72: gasto 13-19/10 | O72: Nekt (Jussara) | Q72: E3 somar a Trusted de Facebook (apos 20/10) | R72: 2026-10-21
A73: Meta Ads | B73: ARENA TINTAS [E-COM + AQUISIÇÃO] | C73: 816285708835072 | D73: Arena Tintas | E73: facebook-ads-omn8 | F73: 1 Funcional — dado ativo | G73: 8412 | H73: 2026-10-20 | I73: 1453.09 | J73: 1453.96 | K73: -0.87 | L73: BRL | M73: gasto 13-19/10 | O73: Nekt (Jussara) | Q73: E3 somar a Trusted de Facebook (apos 20/10) | R73: 2026-10-21
A74: Meta Ads | B74: ARTRIN | C74: 3407674766139167 | D74: CA - Artrin Importadora 02 | E74: facebook-ads-xohe | F74: 1 Funcional — dado ativo | G74: 6739 | H74: 2026-10-20 | I74: 422.1 | J74: 422.1 | K74: 0 | L74: BRL | M74: gasto 13-19/10 | O74: Nekt (Jussara) | Q74: E3 somar a Trusted de Facebook (apos 20/10) | R74: 2026-10-21
A75: Meta Ads | B75: BEST CAR | C75: 235333404360431 | D75: BEST CAR 2024 | E75: facebook-ads-E9RT | F75: 1 Funcional — dado ativo | G75: 8745 | H75: 2026-10-20 | I75: 8356.18 | J75: 8362.24 | K75: -6.06 | L75: BRL | M75: gasto 13-19/10 | O75: — | Q75: ja na Trusted
A76: Meta Ads | B76: BIGAZINE [E-COM + AQUISIÇÃO] | C76: 206891331753918 | D76: BIGAZINE - BOLETO | E76: facebook-ads-tWUr | F76: 1 Funcional — dado ativo | G76: 8022 | H76: 2026-10-20 | I76: 171 | J76: 171.12 | K76: -0.12 | L76: BRL | M76: gasto 13-19/10 | O76: Nekt (Jussara) | Q76: E3 somar a Trusted de Facebook (apos 20/10) | R76: 2026-10-21
A77: Meta Ads | B77: BRAGA (Grupo Completo) | C77: 283877416196277 | D77: CA- Braga Veículos | E77: facebook-ads-8RYU | F77: 1 Funcional — dado ativo | G77: 38413 | H77: 2026-10-20 | I77: 5787.74 | J77: 5789.46 | K77: -1.72 | L77: BRL | M77: gasto 13-19/10 | O77: Nekt (Jussara) | Q77: E3 somar a Trusted de Facebook (apos 20/10) | R77: 2026-10-21
A78: Meta Ads | B78: BRAGA (Grupo Completo) | C78: 566562488446148 | D78: Braga Motors - Carro | E78: facebook-ads-SGls | F78: 1 Funcional — dado ativo | G78: 19114 | H78: 2026-10-20 | I78: 1506.72 | J78: 1507.06 | K78: -0.34 | L78: BRL | M78: gasto 13-19/10 | O78: Nekt (Jussara) | Q78: E3 somar a Trusted de Facebook (apos 20/10) | R78: 2026-10-21
A79: Meta Ads | B79: BRAGA (Grupo Completo) | C79: 463307521829322 | D79: Braga Motors - Motorrad | E79: facebook-ads-lk1y | F79: 1 Funcional — dado ativo | G79: 11193 | H79: 2026-10-20 | I79: 1297.81 | J79: 1297.81 | K79: 0 | L79: BRL | M79: gasto 13-19/10 | O79: Nekt (Jussara) | Q79: E3 somar a Trusted de Facebook (apos 20/10) | R79: 2026-10-21
A80: Meta Ads | B80: BRAGA (Grupo Completo) | C80: 1882475891963192 | D80: Braga Motors - MINI | E80: facebook-ads-Ew4q | F80: 1 Funcional — dado ativo | G80: 10978 | H80: 2026-10-20 | I80: 2261.36 | J80: 2261.37 | K80: -0.01 | L80: BRL | M80: gasto 13-19/10 | O80: Nekt (Jussara) | Q80: E3 somar a Trusted de Facebook (apos 20/10) | R80: 2026-10-21
A81: Meta Ads | B81: BRAGA (Grupo Completo) | C81: 1578951605973326 | D81: CA- Braga Veículos Venda Direta | E81: facebook-ads-CebU | F81: 1 Funcional — dado ativo | G81: 16215 | H81: 2026-10-20 | I81: 803.22 | J81: 803.23 | K81: -0.01 | L81: BRL | M81: gasto 13-19/10 | O81: Nekt (Jussara) | Q81: E3 somar a Trusted de Facebook (apos 20/10) | R81: 2026-10-21
A82: Meta Ads | B82: BRAGA (Grupo Completo) | C82: 1899695863819525 | D82: CA- Braga Acessórios MAO | E82: facebook-ads-Tqjf | F82: 1 Funcional — dado ativo | G82: 38530 | H82: 2026-10-20 | I82: 1082.09 | J82: 1082.11 | K82: -0.02 | L82: BRL | M82: gasto 13-19/10 | O82: Nekt (Jussara) | Q82: E3 somar a Trusted de Facebook (apos 20/10) | R82: 2026-10-21
A83: Meta Ads | B83: BRAGA (Grupo Completo) | C83: 448596103793051 | D83: CA - Braga Motos Rey MAO (ROYAL) | E83: facebook-ads-ezGP | F83: 1 Funcional — dado ativo | G83: 37318 | H83: 2026-10-20 | I83: 1208.56 | J83: 1208.82 | K83: -0.26 | L83: BRL | M83: gasto 13-19/10 | O83: Nekt (Jussara) | Q83: E3 somar a Trusted de Facebook (apos 20/10) | R83: 2026-10-21
A84: Meta Ads | B84: BRAGA (Grupo Completo) | C84: 903840726905396 | D84: CA - Braga Consórcios MAO | E84: facebook-ads-ckhA | F84: 1 Funcional — dado ativo | G84: 20623 | H84: 2026-10-20 | I84: 518.48 | J84: 518.55 | K84: -0.07 | L84: BRL | M84: gasto 13-19/10 | O84: Nekt (Jussara) | Q84: E3 somar a Trusted de Facebook (apos 20/10) | R84: 2026-10-21
A85: Meta Ads | B85: BRAGA (Grupo Completo) | C85: 809512766265620 | D85: CA - Braga Motos Pós Vendas MAO | E85: facebook-ads-smxd | F85: 1 Funcional — dado ativo | G85: 19471 | H85: 2026-10-20 | I85: 223.37 | J85: 223.46 | K85: -0.09 | L85: BRL | M85: gasto 13-19/10 | O85: Nekt (Jussara) | Q85: E3 somar a Trusted de Facebook (apos 20/10) | R85: 2026-10-21
A86: Meta Ads | B86: BRAGA (Grupo Completo) | C86: 1966625676863140 | D86: CA- Braga Veículos Pós Vendas | E86: facebook-ads-kQ2S | F86: 1 Funcional — dado ativo | G86: 25464 | H86: 2026-10-20 | I86: 759.28 | J86: 759.72 | K86: -0.44 | L86: BRL | M86: gasto 13-19/10 | O86: — | Q86: ja na Trusted
A87: Meta Ads | B87: BRAGA (Grupo Completo) | C87: 1172209193972759 | D87: CA- Braga Motos MAO | E87: facebook-ads-GWZ2 | F87: 1 Funcional — dado ativo | G87: 39326 | H87: 2026-10-20 | I87: 2020.39 | J87: 2021.58 | K87: -1.19 | L87: BRL | M87: gasto 13-19/10 | O87: — | Q87: ja na Trusted
A88: Meta Ads | B88: CAA ALUMÍNIO | C88: 3384094671807625 | D88: CAA | ALUMÍNIO | E88: facebook-ads-WQmP | F88: 1 Funcional — dado ativo | G88: 6033 | H88: 2026-10-20 | I88: 74.41 | J88: 74.43 | K88: -0.02 | L88: BRL | M88: gasto 13-19/10 | O88: Nekt (Jussara) | Q88: E3 somar a Trusted de Facebook (apos 20/10) | R88: 2026-10-21
A89: Meta Ads | B89: CAA TINTAS | C89: 1439421523351648 | D89: CAA | TINTAS EXPRESS | E89: facebook-ads-K2kh | F89: 1 Funcional — dado ativo | G89: 3164 | H89: 2026-10-19 | I89: 209.69 | J89: 209.69 | K89: 0 | L89: BRL | M89: gasto 13-19/10 | O89: Nekt (Jussara) | Q89: E3 somar a Trusted de Facebook (apos 20/10) | R89: 2026-10-21
A90: Meta Ads | B90: CDL MANAUS | C90: 474967098302512 | D90: CDL MANAUS | E90: facebook-ads-oVkz | F90: 1 Funcional — dado ativo | G90: 2453 | H90: 2026-10-20 | I90: 476.78 | J90: 476.79 | K90: -0.01 | L90: BRL | M90: gasto 13-19/10 | O90: Nekt (Jussara) | Q90: E3 somar a Trusted de Facebook (apos 20/10) | R90: 2026-10-21
A91: Meta Ads | B91: COLMEIA | C91: 781268383219049 | D91: Colmeia - Cartão | E91: facebook-ads-ln1a | F91: 1 Funcional — dado ativo | G91: 25593 | H91: 2026-10-20 | I91: 7845.19 | J91: 7848.09 | K91: -2.9 | L91: BRL | M91: gasto 13-19/10 | O91: — | Q91: ja na Trusted
A92: Meta Ads | B92: COMAC | C92: 180454263287280 | D92: Comac | E92: facebook-ads-rPr1 | F92: 1 Funcional — dado ativo | G92: 5689 | H92: 2026-10-20 | I92: 293.49 | J92: 293.5 | K92: -0.01 | L92: BRL | M92: gasto 13-19/10 | O92: Nekt (Jussara) | Q92: E3 somar a Trusted de Facebook (apos 20/10) | R92: 2026-10-21
A93: Meta Ads | B93: CONSTRÓI INCORPORADORA | C93: 526683429550109 | D93: Constroi ADS | E93: facebook-ads-oB7d | F93: 1 Funcional — dado ativo | G93: 11610 | H93: 2026-10-20 | I93: 3759.93 | J93: 3761.65 | K93: -1.72 | L93: BRL | M93: gasto 13-19/10 | O93: — | Q93: ja na Trusted
A94: Meta Ads | B94: Consórcio Chevrolet | C94: 291639228868958 | D94: Consórcio Chevrolet | E94: facebook-ads-ofJE | F94: 1 Funcional — dado ativo | G94: 14714 | H94: 2026-10-20 | I94: 926.85 | J94: 926.88 | K94: -0.03 | L94: BRL | M94: gasto 13-19/10 | O94: Nekt (Jussara) | Q94: E3 somar a Trusted de Facebook (apos 20/10) | R94: 2026-10-21
A95: Meta Ads | B95: DR. CABRAL | C95: 1487130863198154 | D95: Cabral v2 | E95: facebook-ads-tzO2 | F95: 1 Funcional — dado ativo | G95: 2456 | H95: 2026-10-20 | I95: 763.91 | J95: 763.91 | K95: 0 | L95: BRL | M95: gasto 13-19/10 | O95: Nekt (Jussara) | Q95: E3 somar a Trusted de Facebook (apos 20/10) | R95: 2026-10-21
A96: Meta Ads | B96: HAGE | C96: 971212355687773 | D96: Grupo Hage Alimentos | E96: facebook-ads-pbon | F96: 1 Funcional — dado ativo | G96: 521 | H96: 2026-10-20 | I96: 627.94 | J96: 628.01 | K96: -0.07 | L96: BRL | M96: gasto 13-19/10 | O96: Nekt (Jussara) | Q96: E3 somar a Trusted de Facebook (apos 20/10) | R96: 2026-10-21
A97: Meta Ads | B97: HOSPITAL SANTA JÚLIA | C97: 100906227323525 | D97: Hospital Santa Júlia Ads | E97: facebook-ads-DtiV | F97: 1 Funcional — dado ativo | G97: 7351 | H97: 2026-10-13 | I97: 0 | J97: 0 | K97: 0 | L97: BRL | M97: gasto 13-19/10 | O97: Nekt (Jussara) | Q97: E3 somar a Trusted de Facebook (apos 20/10) | R97: 2026-10-21
A98: Meta Ads | B98: INFORCELL | C98: 1880827672299516 | D98: CA INFORCELL - OFICIAL | E98: facebook-ads-5eAs | F98: 1 Funcional — dado ativo | G98: 1587 | H98: 2026-10-20 | I98: 706.84 | J98: 706.85 | K98: -0.01 | L98: BRL | M98: gasto 13-19/10 | O98: Nekt (Jussara) | Q98: E3 somar a Trusted de Facebook (apos 20/10) | R98: 2026-10-21
A99: Meta Ads | B99: Japurá Pneus | C99: 728255493211287 | D99: Japurá Pneus | E99: facebook-ads-GZtZ | F99: 1 Funcional — dado ativo | G99: 3193 | H99: 2026-10-16 | I99: 540.22 | J99: 540.22 | K99: 0 | L99: BRL | M99: gasto 13-19/10 | O99: Nekt (Jussara) | Q99: E3 somar a Trusted de Facebook (apos 20/10) | R99: 2026-10-21
A100: Meta Ads | B100: KIFFER | C100: 2368278856934990 | D100: Kiffer - ADS | E100: facebook-ads-Uu0D | F100: 1 Funcional — dado ativo | G100: 1134 | H100: 2026-10-20 | I100: 181.89 | J100: 181.89 | K100: 0 | L100: BRL | M100: gasto 13-19/10 | O100: Nekt (Jussara) | Q100: E3 somar a Trusted de Facebook (apos 20/10) | R100: 2026-10-21
A101: Meta Ads | B101: LEAP MOTORS | C101: 1380362517366530 | D101: Leapmotor VM I Reserva | E101: facebook-ads-elFk | F101: 1 Funcional — dado ativo | G101: 274 | H101: 2026-10-20 | I101: 126.69 | J101: 126.98 | K101: -0.29 | L101: BRL | M101: gasto 13-19/10 | O101: Nekt (Jussara) | Q101: E3 somar a Trusted de Facebook (apos 20/10) | R101: 2026-10-21
A102: Meta Ads | B102: MILLENIUM | C102: 1397293557166269 | D102: Millennium Ads | E102: facebook-ads-hIaw | F102: 1 Funcional — dado ativo | G102: 3559 | H102: 2026-10-20 | I102: 248.03 | J102: 248.07 | K102: -0.04 | L102: BRL | M102: gasto 13-19/10 | O102: Nekt (Jussara) | Q102: E3 somar a Trusted de Facebook (apos 20/10) | R102: 2026-10-21
A103: Meta Ads | B103: MOVE RENTAL CARS | C103: 541763807067071 | D103: CA1 - Move Rental Cars | E103: facebook-ads-mtAO | F103: 1 Funcional — dado ativo | G103: 7872 | H103: 2026-10-20 | I103: 570.41 | J103: 570.41 | K103: 0 | L103: USD | M103: gasto 13-19/10 | O103: Nekt (Jussara) | Q103: E3 somar a Trusted de Facebook (apos 20/10) | R103: 2026-10-21
A104: Meta Ads | B104: Neo Vila Adrianopolis Empreendimento Ads | C104: 961762058045583 | D104: Neo Vila Adrianopolis Empreendimento Ads | E104: facebook-ads-b8KQ | F104: 1 Funcional — dado ativo | G104: 5957 | H104: 2026-10-20 | I104: 369.65 | J104: 369.73 | K104: -0.08 | L104: BRL | M104: gasto 13-19/10 | O104: Nekt (Jussara) | Q104: E3 somar a Trusted de Facebook (apos 20/10) | R104: 2026-10-21
A105: Meta Ads | B105: PMZ ESCOLA DE MECÂNICOS | C105: 479374257875979 | D105: Escola para Mecânicos | E105: facebook-ads-oih2 | F105: 1 Funcional — dado ativo | G105: 7269 | H105: 2026-10-20 | I105: 685.91 | J105: 686.2 | K105: -0.29 | L105: BRL | M105: gasto 13-19/10 | O105: Nekt (Jussara) | Q105: E3 somar a Trusted de Facebook (apos 20/10) | R105: 2026-10-21
A106: Meta Ads | B106: PMZ GRUPO ECOMM | C106: 143457285456847 | D106: PMZ GRUPO ECOMM | E106: facebook-ads-Vgli | F106: 1 Funcional — dado ativo | G106: 3877 | H106: 2026-10-20 | I106: 7455.86 | J106: 7456.17 | K106: -0.31 | L106: BRL | M106: gasto 13-19/10 | O106: Nekt (Jussara) | Q106: E3 somar a Trusted de Facebook (apos 20/10) | R106: 2026-10-21
A107: Meta Ads | B107: PMZ GRUPO LOJA | C107: 839811160322414 | D107: PMZ GRUPO LOJA | E107: facebook-ads-x4yO | F107: 1 Funcional — dado ativo | G107: 14740 | H107: 2026-10-20 | I107: 4996.29 | J107: 4996.93 | K107: -0.64 | L107: BRL | M107: gasto 13-19/10 | O107: — | Q107: ja na Trusted
A108: Meta Ads | B108: PNEU EXPRESS | C108: 3540348596114929 | D108: Pneu Express | E108: facebook-ads-2vvw | F108: 1 Funcional — dado ativo | G108: 586 | H108: 2026-10-20 | I108: 508.77 | J108: 508.78 | K108: -0.01 | L108: BRL | M108: gasto 13-19/10 | O108: Nekt (Jussara) | Q108: E3 somar a Trusted de Facebook (apos 20/10) | R108: 2026-10-21
A109: Meta Ads | B109: PNEU FORTE DISTRIBUIDORA | C109: 1725052584888400 | D109: Pneu Forte | Distribuidora | E109: facebook-ads-s8I1 | F109: 1 Funcional — dado ativo | G109: 2137 | H109: 2026-10-20 | I109: 536.67 | J109: 536.67 | K109: 0 | L109: BRL | M109: gasto 13-19/10 | O109: Nekt (Jussara) | Q109: E3 somar a Trusted de Facebook (apos 20/10) | R109: 2026-10-21
A110: Meta Ads | B110: PNEU FORTE VAREJO | C110: 1813722919392589 | D110: Pneu Forte | Varejo | E110: facebook-ads-phtv | F110: 1 Funcional — dado ativo | G110: 3062 | H110: 2026-10-20 | I110: 194.29 | J110: 194.31 | K110: -0.02 | L110: BRL | M110: gasto 13-19/10 | O110: Nekt (Jussara) | Q110: E3 somar a Trusted de Facebook (apos 20/10) | R110: 2026-10-21
A111: Meta Ads | B111: Parque das Torres Ads | C111: 1284883625966129 | D111: Parque das Torres Ads | E111: facebook-ads-jZBq | F111: 1 Funcional — dado ativo | G111: 9582 | H111: 2026-10-20 | I111: 690.14 | J111: 690.14 | K111: 0 | L111: BRL | M111: gasto 13-19/10 | O111: Nekt (Jussara) | Q111: E3 somar a Trusted de Facebook (apos 20/10) | R111: 2026-10-21
...

Sheet Cobertura
A1: Plataforma | B1: Aplicáveis | C1: Conectadas | D1: Leitura confirmada | E1: Dado ativo | F1: Pendentes | G1: Bloqueadas | H1: Sem conexão | I1: % conectadas | J1: % leitura confirmada | K1: % dado ativo
A2: Meta Ads | B2: =COUNTIFS(Contas!$A$2:$A$243,$A2,Contas!$F$2:$F$243,"<>6*",Contas!$F$2:$F$243,"<>8*") | C2: =COUNTIFS(Contas!$A$2:$A$243,$A2,Contas!$F$2:$F$243,"1*")+COUNTIFS(Contas!$A$2:$A$243,$A2,Contas!$F$2:$F$243,"2*")+COUNTIFS(Contas!$A$2:$A$243,$A2,Contas!$F$2:$F$243,"3*") | D2: =COUNTIFS(Contas!$A$2:$A$243,$A2,Contas!$F$2:$F$243,"1*")+COUNTIFS(Contas!$A$2:$A$243,$A2,Contas!$F$2:$F$243,"2*") | E2: =COUNTIFS(Contas!$A$2:$A$243,$A2,Contas!$F$2:$F$243,"1*") | F2: =COUNTIFS(Contas!$A$2:$A$243,$A2,Contas!$F$2:$F$243,"4*") | G2: =COUNTIFS(Contas!$A$2:$A$243,$A2,Contas!$F$2:$F$243,"5*") | H2: =COUNTIFS(Contas!$A$2:$A$243,$A2,Contas!$F$2:$F$243,"7*") | I2: =IFERROR(C2/B2,0) | J2: =IFERROR(D2/B2,0) | K2: =IFERROR(E2/B2,0)
A3: Google Ads | B3: =COUNTIFS(Contas!$A$2:$A$243,$A3,Contas!$F$2:$F$243,"<>6*",Contas!$F$2:$F$243,"<>8*") | C3: =COUNTIFS(Contas!$A$2:$A$243,$A3,Contas!$F$2:$F$243,"1*")+COUNTIFS(Contas!$A$2:$A$243,$A3,Contas!$F$2:$F$243,"2*")+COUNTIFS(Contas!$A$2:$A$243,$A3,Contas!$F$2:$F$243,"3*") | D3: =COUNTIFS(Contas!$A$2:$A$243,$A3,Contas!$F$2:$F$243,"1*")+COUNTIFS(Contas!$A$2:$A$243,$A3,Contas!$F$2:$F$243,"2*") | E3: =COUNTIFS(Contas!$A$2:$A$243,$A3,Contas!$F$2:$F$243,"1*") | F3: =COUNTIFS(Contas!$A$2:$A$243,$A3,Contas!$F$2:$F$243,"4*") | G3: =COUNTIFS(Contas!$A$2:$A$243,$A3,Contas!$F$2:$F$243,"5*") | H3: =COUNTIFS(Contas!$A$2:$A$243,$A3,Contas!$F$2:$F$243,"7*") | I3: =IFERROR(C3/B3,0) | J3: =IFERROR(D3/B3,0) | K3: =IFERROR(E3/B3,0)
A4: RD Station | B4: =COUNTIFS(Contas!$A$2:$A$243,$A4,Contas!$F$2:$F$243,"<>6*",Contas!$F$2:$F$243,"<>8*") | C4: =COUNTIFS(Contas!$A$2:$A$243,$A4,Contas!$F$2:$F$243,"1*")+COUNTIFS(Contas!$A$2:$A$243,$A4,Contas!$F$2:$F$243,"2*")+COUNTIFS(Contas!$A$2:$A$243,$A4,Contas!$F$2:$F$243,"3*") | D4: =COUNTIFS(Contas!$A$2:$A$243,$A4,Contas!$F$2:$F$243,"1*")+COUNTIFS(Contas!$A$2:$A$243,$A4,Contas!$F$2:$F$243,"2*") | E4: =COUNTIFS(Contas!$A$2:$A$243,$A4,Contas!$F$2:$F$243,"1*") | F4: =COUNTIFS(Contas!$A$2:$A$243,$A4,Contas!$F$2:$F$243,"4*") | G4: =COUNTIFS(Contas!$A$2:$A$243,$A4,Contas!$F$2:$F$243,"5*") | H4: =COUNTIFS(Contas!$A$2:$A$243,$A4,Contas!$F$2:$F$243,"7*") | I4: =IFERROR(C4/B4,0) | J4: =IFERROR(D4/B4,0) | K4: =IFERROR(E4/B4,0)
A5: TikTok Ads | B5: =COUNTIFS(Contas!$A$2:$A$243,$A5,Contas!$F$2:$F$243,"<>6*",Contas!$F$2:$F$243,"<>8*") | C5: =COUNTIFS(Contas!$A$2:$A$243,$A5,Contas!$F$2:$F$243,"1*")+COUNTIFS(Contas!$A$2:$A$243,$A5,Contas!$F$2:$F$243,"2*")+COUNTIFS(Contas!$A$2:$A$243,$A5,Contas!$F$2:$F$243,"3*") | D5: =COUNTIFS(Contas!$A$2:$A$243,$A5,Contas!$F$2:$F$243,"1*")+COUNTIFS(Contas!$A$2:$A$243,$A5,Contas!$F$2:$F$243,"2*") | E5: =COUNTIFS(Contas!$A$2:$A$243,$A5,Contas!$F$2:$F$243,"1*") | F5: =COUNTIFS(Contas!$A$2:$A$243,$A5,Contas!$F$2:$F$243,"4*") | G5: =COUNTIFS(Contas!$A$2:$A$243,$A5,Contas!$F$2:$F$243,"5*") | H5: =COUNTIFS(Contas!$A$2:$A$243,$A5,Contas!$F$2:$F$243,"7*") | I5: =IFERROR(C5/B5,0) | J5: =IFERROR(D5/B5,0) | K5: =IFERROR(E5/B5,0)
A6: LinkedIn Ads | B6: =COUNTIFS(Contas!$A$2:$A$243,$A6,Contas!$F$2:$F$243,"<>6*",Contas!$F$2:$F$243,"<>8*") | C6: =COUNTIFS(Contas!$A$2:$A$243,$A6,Contas!$F$2:$F$243,"1*")+COUNTIFS(Contas!$A$2:$A$243,$A6,Contas!$F$2:$F$243,"2*")+COUNTIFS(Contas!$A$2:$A$243,$A6,Contas!$F$2:$F$243,"3*") | D6: =COUNTIFS(Contas!$A$2:$A$243,$A6,Contas!$F$2:$F$243,"1*")+COUNTIFS(Contas!$A$2:$A$243,$A6,Contas!$F$2:$F$243,"2*") | E6: =COUNTIFS(Contas!$A$2:$A$243,$A6,Contas!$F$2:$F$243,"1*") | F6: =COUNTIFS(Contas!$A$2:$A$243,$A6,Contas!$F$2:$F$243,"4*") | G6: =COUNTIFS(Contas!$A$2:$A$243,$A6,Contas!$F$2:$F$243,"5*") | H6: =COUNTIFS(Contas!$A$2:$A$243,$A6,Contas!$F$2:$F$243,"7*") | I6: =IFERROR(C6/B6,0) | J6: =IFERROR(D6/B6,0) | K6: =IFERROR(E6/B6,0)
A7: Spotify Ads | B7: =COUNTIFS(Contas!$A$2:$A$243,$A7,Contas!$F$2:$F$243,"<>6*",Contas!$F$2:$F$243,"<>8*") | C7: =COUNTIFS(Contas!$A$2:$A$243,$A7,Contas!$F$2:$F$243,"1*")+COUNTIFS(Contas!$A$2:$A$243,$A7,Contas!$F$2:$F$243,"2*")+COUNTIFS(Contas!$A$2:$A$243,$A7,Contas!$F$2:$F$243,"3*") | D7: =COUNTIFS(Contas!$A$2:$A$243,$A7,Contas!$F$2:$F$243,"1*")+COUNTIFS(Contas!$A$2:$A$243,$A7,Contas!$F$2:$F$243,"2*") | E7: =COUNTIFS(Contas!$A$2:$A$243,$A7,Contas!$F$2:$F$243,"1*") | F7: =COUNTIFS(Contas!$A$2:$A$243,$A7,Contas!$F$2:$F$243,"4*") | G7: =COUNTIFS(Contas!$A$2:$A$243,$A7,Contas!$F$2:$F$243,"5*") | H7: =COUNTIFS(Contas!$A$2:$A$243,$A7,Contas!$F$2:$F$243,"7*") | I7: =IFERROR(C7/B7,0) | J7: =IFERROR(D7/B7,0) | K7: =IFERROR(E7/B7,0)
A8: Twitter/X Ads | B8: =COUNTIFS(Contas!$A$2:$A$243,$A8,Contas!$F$2:$F$243,"<>6*",Contas!$F$2:$F$243,"<>8*") | C8: =COUNTIFS(Contas!$A$2:$A$243,$A8,Contas!$F$2:$F$243,"1*")+COUNTIFS(Contas!$A$2:$A$243,$A8,Contas!$F$2:$F$243,"2*")+COUNTIFS(Contas!$A$2:$A$243,$A8,Contas!$F$2:$F$243,"3*") | D8: =COUNTIFS(Contas!$A$2:$A$243,$A8,Contas!$F$2:$F$243,"1*")+COUNTIFS(Contas!$A$2:$A$243,$A8,Contas!$F$2:$F$243,"2*") | E8: =COUNTIFS(Contas!$A$2:$A$243,$A8,Contas!$F$2:$F$243,"1*") | F8: =COUNTIFS(Contas!$A$2:$A$243,$A8,Contas!$F$2:$F$243,"4*") | G8: =COUNTIFS(Contas!$A$2:$A$243,$A8,Contas!$F$2:$F$243,"5*") | H8: =COUNTIFS(Contas!$A$2:$A$243,$A8,Contas!$F$2:$F$243,"7*") | I8: =IFERROR(C8/B8,0) | J8: =IFERROR(D8/B8,0) | K8: =IFERROR(E8/B8,0)
A9: Total | B9: =SUM(B2:B8) | C9: =SUM(C2:C8) | D9: =SUM(D2:D8) | E9: =SUM(E2:E8) | F9: =SUM(F2:F8) | G9: =SUM(G2:G8) | H9: =SUM(H2:H8) | I9: =C9/B9 | J9: =D9/B9 | K9: =E9/B9
A10: Meta + Google (confirmadas contra a plataforma) | B10: =B2+B3 | C10: =C2+C3 | D10: =D2+D3 | E10: =E2+E3 | F10: =F2+F3 | G10: =G2+G3 | H10: 0 | I10: =C10/B10 | J10: =D10/B10 | K10: =E10/B10
A12: COBERTURA POR GASTO (reais) | B12: Gasto das contas com leitura confirmada | C12: Gasto total da plataforma (MCC) | D12: % coberto | E12: Janela | F12: Observação
A13: Meta Ads | B13: =SUMIFS(Contas!$J$2:$J$243,Contas!$A$2:$A$243,"Meta Ads",Contas!$F$2:$F$243,"1*",Contas!$L$2:$L$243,"BRL")+SUMIFS(Contas!$J$2:$J$243,Contas!$A$2:$A$243,"Meta Ads",Contas!$F$2:$F$243,"2*",Contas!$L$2:$L$243,"BRL") | C13: 111727.79 | D13: =B13/C13 | E13: 13–19/10 (7 dias) | F13: 286 contas do MCC da Meta, relidas em 21/10 (uma devolveu 403); inclui conta nova 1675573549548233 (R$ 758,34) fora do inventário
A14: Google Ads (sem Nova Era, ex-clientes e inativos) | B14: =SUMIFS(Contas!$J$2:$J$243,Contas!$A$2:$A$243,"Google Ads",Contas!$F$2:$F$243,"1*",Contas!$L$2:$L$243,"BRL")+SUMIFS(Contas!$J$2:$J$243,Contas!$A$2:$A$243,"Google Ads",Contas!$F$2:$F$243,"2*",Contas!$L$2:$L$243,"BRL") | C14: 104743.53 | D14: =B14/C14 | E14: 13/09–12/10 (30 dias) | F14: REFERÊNCIA DE 16/10 (MCC do Google não consultado hoje); a Nekt foi re-medida em 21/10; denominador sem as 5 contas Nova Era e sem 8 contas de ex-clientes, inativos, duplicidade e decisão
A15: Google Ads (com Nova Era, ex-clientes e inativos no denominador) | B15: =B14 | C15: 156648.99 | D15: =B15/C15 | E15: 13/09–12/10 | F15: Mostra o efeito de essas contas ainda estarem vinculadas ao MCC: o salto de 71,2% (15/10) para 97,1% (16/10) vem do denominador
A17: SANEAMENTO (outra medida) | B17: Regras conformes | C17: Regras publicadas | D17: % | E17: Fonte | F17: Observação
A18: Qualidade do dado que já chegou | B18: 1483 | C18: 1485 | D18: =B18/C18 | E18: tabelas de resultado das 37 suítes, 21/10 | F18: Não mede contas ausentes; 1 alerta (grupo_anuncio.campanha_catalogada) e 1 bloqueante (vbot_wl_simples.carga_do_mesmo_dia)
A19: Fontes publicadas com sucesso na última execução | B19: 282 | C19: 300 | D19: =B19/C19 | E19: varredura de 21/10 (~09h de Manaus) | F19: Saúde de pipeline; sucesso não prova dado. 300 publicadas = 252 + 48 de Instagram e Páginas

Sheet Instagram e Páginas
A1: Tipo | B1: Descrição da fonte | C1: Fonte | D1: Camada | E1: Conta / página | F1: Seguidores | G1: Posts na conta | H1: Posts extraídos (tabela media / posts) | I1: Tabelas com linhas | J1: Tabelas não materializadas | K1: Última execução | L1: Gatilho | M1: Situação
A2: Instagram | B2: Instagram - Braga Motors - SM | C2: instagram-CfH8 | D2: vanguardamartech_braga_motors_instagram | E2: bragamotors.bmw | F2: 781 | G2: 437 | H2: 9 | I2: 12 de 15 | J2: 1 | K2: success | L2: manual | M2: Conectada — extração mínima
A3: Instagram | B3: Instagram - Braga Acessorios - SM | C3: instagram-IZTB | D3: vanguardamartech_braga_acessorios_instagram | E3: bragaacessorios.cidadenova | F3: 3658 | G3: 438 | H3: 7 | I3: 12 de 15 | J3: 1 | K3: success | L3: manual | M3: Conectada — extração mínima
A4: Instagram | B4: Instagram - BAP - SM | C4: instagram-bv3u | D4: vanguardamartech_bap_instagram | E4: bapautoparts | F4: 1113 | G4: 101 | H4: 2 | I4: 12 de 15 | J4: 1 | K4: success | L4: manual | M4: Conectada — extração mínima
A5: Instagram | B5: Instagram - Bajaj - SM | C5: instagram-209E | D5: vanguardamartech_bajaj_instagram | E5: bajajmanausvega | F5: 9442 | G5: 500 | H5: 1 | I5: 12 de 15 | J5: 1 | K5: success | L5: manual | M5: Conectada — extração mínima
A6: Instagram | B6: Instagram - BA Eletrica - SM | C6: instagram-JJJ4 | D6: vanguardamartech_ba_eletrica_instagram | E6: baeletrica | F6: 34603 | G6: 4278 | H6: 8 | I6: 14 de 15 | J6: 1 | K6: success | L6: manual | M6: Conectada — extração mínima
A7: Instagram | B7: Instagram - Automaster - SM | C7: instagram-rdCK | D7: vanguardamartech_automaster_instagram | E7: consorciochevroletmanaus | F7: 7658 | G7: 196 | H7: 0 | I7: 10 de 15 | J7: 4 | K7: success | L7: manual | M7: Conectada — extração mínima
A8: Instagram | B8: Instagram - AMZ Geradores - SM | C8: instagram-gWSW | D8: vanguardamartech_amz_geradores_instagram | E8: amzgeradores | F8: 2983 | G8: 543 | H8: 1 | I8: 12 de 15 | J8: 1 | K8: success | L8: manual | M8: Conectada — extração mínima
A9: Instagram | B9: Instagram - Amazoncopy - SM | C9: instagram-K8dK | D9: vanguardamartech_amazoncopy_instagram | E9: amazonascopiadoras | F9: 3419 | G9: 751 | H9: 2 | I9: 12 de 15 | J9: 1 | K9: success | L9: manual | M9: Conectada — extração mínima
A10: Instagram | B10: Instagram - Amazon Open Mall - SM | C10: instagram-CeJD | D10: vanguardamartech_amazon_open_mall_instagram | E10: amazon_openmall | F10: 12976 | G10: 263 | H10: 1 | I10: 12 de 15 | J10: 1 | K10: success | L10: manual | M10: Conectada — extração mínima
A11: Instagram | B11: Instagram - Acesso Saúde - SM | C11: instagram-Wajn | D11: vanguardamartech_acesso_saude_instagram | E11: acessosaudemanaus | F11: 58082 | G11: 1886 | H11: 6 | I11: 12 de 15 | J11: 1 | K11: success | L11: manual | M11: Conectada — extração mínima
A12: Instagram | B12: Instagram - AC Display - SM | C12: instagram-oMgW | D12: vanguardamartech_ac_display_instagram | E12: acdisplay | F12: 1041 | G12: 239 | H12: 2 | I12: 12 de 15 | J12: 1 | K12: success | L12: manual | M12: Conectada — extração mínima
A13: Facebook Pages | B13: Facebook - Braga Veiculos VD | C13: facebook-pages-GyYt | D13: vanguardamartech_braga_veiculos_venda_direta_facebook | E13: Braga Veículos - Venda Direta | H13: 0 | I13: 3 de 8 | J13: 0 | K13: success | L13: manual | M13: Conectada — dado presente
A14: Facebook Pages | B14: Facebook - Braga Veículos Varejo e Pós-venda | C14: facebook-pages-nKAw | D14: vanguardamartech_braga_veiculos_varejo_e_vd_facebook | E14: Braga Veículos; 1 falha anterior em 2026-10-15T00:50:59 | H14: 1 | I14: 7 de 8 | J14: 0 | K14: success | L14: manual | M14: Conectada — dado presente
A15: Facebook Pages | B15: Facebook - Braga Acessorios | C15: facebook-pages-l1QS | D15: vanguardamartech_braga_acessorios_facebook | E15: Braga Acessórios MAO | H15: 0 | I15: 3 de 8 | J15: 0 | K15: success | L15: manual | M15: Conectada — dado presente
A16: Facebook Pages | B16: Facebook Linvest | C16: facebook-pages-KJVl | D16: vanguardamartech_linvest_facebook | E16: Linvest | H16: 1 | I16: 6 de 8 | J16: 0 | K16: success | L16: manual | M16: Conectada — dado presente
A17: Facebook Pages | B17: Facebook Steel port | C17: facebook-pages-NnRq | D17: vanguardamartech_steel_port_facebook | E17: Steel Port | H17: 1 | I17: 6 de 8 | J17: 0 | K17: success | L17: manual | M17: Conectada — dado presente
A18: Facebook Pages | B18: Facebook Hage | C18: facebook-pages-9O6v | D18: vanguardamartech_hage_facebook | E18: Grupo Hage | H18: 1 | I18: 6 de 8 | J18: 0 | K18: success | L18: manual | M18: Conectada — dado presente
A19: Facebook Pages | B19: Facebook - Vbot | C19: facebook-pages-hZNd | D19: vanguardamartech_vbot_facebook | E19: Vbot.app | H19: 0 | I19: 3 de 8 | J19: 0 | K19: success | L19: manual | M19: Conectada — dado presente
A20: Facebook Pages | B20: Facebook Amazon Open Mall | C20: facebook-pages-qhR9 | D20: vanguardamartech_amazon_open_mall_facebook | E20: Amazon Open Mall | H20: 1 | I20: 6 de 8 | J20: 0 | K20: success | L20: manual | M20: Conectada — dado presente
A21: Facebook Pages | B21: Facebook AC Display | C21: facebook-pages-QnG2 | D21: vanguardamartech_acdisplay_facebook | E21: AC Display | H21: 1 | I21: 6 de 8 | J21: 0 | K21: success | L21: manual | M21: Conectada — dado presente
A22: Facebook Pages | B22: Facebook BAP | C22: facebook-pages-9q2u | D22: vanguardamartech_bap_facebook | E22: BAP AUTO PARTS | H22: 0 | I22: 3 de 8 | J22: 0 | K22: success | L22: manual | M22: Conectada — dado presente
A23: Facebook Pages | B23: Facebook de Acesso Saúde | C23: facebook-pages-c7VF | D23: vanguardamartech_acesso_saude_facebook | E23: Acesso Saúde - Manaus | H23: 1 | I23: 7 de 8 | J23: 0 | K23: success | L23: manual | M23: Conectada — dado presente
A24: Facebook Pages | B24: Facebook - Animativ | C24: facebook-pages-Xedv | D24: vanguardamartech_animativ_facebook | E24: Animativ Vitaminas | H24: 0 | I24: 3 de 8 | J24: 0 | K24: success | L24: manual | M24: Conectada — dado presente
A25: Facebook Pages | B25: Facebook Vanguarda | C25: facebook-pages-PPsY | D25: (não identificada) | I25: 0 de 1 | J25: 0 | K25: success | L25: manual | M25: Conectada — sem camada identificada, não medida
A26: Facebook Pages | B26: Fonte das páginas do facebook dos clientes | C26: facebook-pages-ftS8 | D26: (não identificada) | I26: 0 de 1 | J26: 0 | K26: success | L26: manual | M26: Conectada — sem camada identificada, não medida
A27: Instagram | B27: Instagram - Braga Veiculos Venda Direta - SM | C27: instagram-wRZ1 | I27: — | J27: 0 | K27: rascunho | L27: — | M27: Rascunho (sem execução)
A29: NOTA 21/10: esta aba lista as 60 fontes medidas em 15–16/10 (12 de Instagram e 48 de Páginas, com a linha de Instagram da época). Em 21/10 há 108 fontes (54 + 54); as 48 acrescentadas não foram medidas quanto a dado nem estão nas Trusted (listas fixas de 12 contas e 48 páginas). Todas manuais.

Sheet Sistemas internos
A1: Sistema | B1: Fonte(s) na Nekt | C1: Situação | D1: Cadência | E1: Dado medido (15/10; iClips: 21/10) | F1: Camada tratada | G1: Impedimento
A2: VJOB (sistema real, MySQL) | B2: mysql-yIOn | C2: Funcional — dado ativo | D2: domingo 00:00 (+ passadas manuais) | E2: 206.946 escopos, 317 clientes, 2.239 jobs, 10.160 parcelas (carga de 14/10) | F2: Trusted e Refined | G2: 16 streams com credencial na Raw (decisão de exclusão é da Nekt/backoffice)
A3: iClips (projetos, peças, apontamento) | B3: notebook-Rbpo + rest-api-xk4P (apoio) + rest-api-73hk (projetos) | C3: Bloqueada | D3: notebook inativo desde 19/10; apoio diária (falhando); 73hk semanal (falhando) | E3: 12.125 projetos, 134.864 peças, 6.186 apontamentos (última carga de 19/10) | F3: Trusted e Refined, sem atualização | G3: API key recusada (401) em 19, 20 e 21/10; 73hk com 3 falhas seguidas e último sucesso em 28/09
A4: Conexa (VBOT) | B4: supabase-x0tz (88 streams) | C4: Funcional — dado ativo | D4: diária 01:00 | E4: 1.018 cobranças (carga de 15/10) | F4: Trusted e Refined | G4: —
A5: Conta Azul (razão e espelho) | B5: supabase-x0tz + mysql-yIOn | C5: Funcional — dado ativo | D5: diária / semanal | E5: 7.097 movimentos (carga de 14/10) | F5: Trusted e Refined | G5: Razão só tem baixa a partir de 25/05/2026
A6: Financeiro (iClips) | B6: supabase-x0tz | C6: Funcional — dado ativo | D6: diária 01:00 | E6: 45.154 movimentos (carga de 15/10) | F6: Trusted e Refined | G6: Cobre até 2026-05; a partir de junho o razão passou para o Conta Azul
A7: PI (pedidos de inserção) | B7: supabase-x0tz | C7: Funcional — dado ativo | D7: diária 01:00 | E7: 3.348 PIs (carga de 15/10) | F7: Trusted e Refined | G7: —
A8: Gmail (2 caixas) | B8: gmail-cF2Q + gmail-c3ku | C8: Funcional — dado ativo | D8: diária 05:00 / semanal | E8: 33.517 mensagens (carga de 15/10) | F8: Trusted e Refined | G8: —
A9: Linear | B9: linear-byrt | C9: Funcional — dado ativo (histórico) | D9: diária 04:20 | E9: 230 issues; última atividade em 01/08/2026 | F9: Trusted e Refined | G9: A equipe deixou de usar o Linear; o dado é histórico
A10: GitHub | B10: github-2Upt | C10: Conectada — sem confirmação | D10: semanal domingo 01:00 | E10: 0 linhas (medido em 15/10); execuções com sucesso e nenhum registro (última em 14/10) | F10: Trusted e Refined existem, sem tabela | G10: Causa só se vê na interface (lista de repositórios ou data inicial do conector)
A11: WhatsApp (Z-API, webhook) | B11: webhook-v2-nZdJ | C11: Conectada — sem confirmação | D11: diária 07:00 | E11: 0 linhas (medido em 15/10); vazio desde 28/09 | F11: — | G11: URL e x-api-key precisam ser configurados na instância da Z-API
A12: Semrush | B12: semrush-OnLY | C12: Bloqueada | D12: inativa | E12: sem sucesso desde sempre (7 falhas) | F12: — | G12: Chave de API rejeitada (403 WRONG KEY-ID PAIR)
... A15: Quickin | B15: sem fonte | C15: Sem fonte | D15: — | E15: — | F15: — | G15: Idem Qulture

Sheet Impedimentos
A1: ID | B1: Impedimento | C1: Plataforma | D1: Contas | E1: Exposição (gasto na janela) | F1: Causa medida | G1: O que destrava | H1: Responsável (a confirmar) | I1: Prazo duro | J1: Previsão (proposta) | K1: Prioridade | L1: Etapa | M1: Consequência
A2: I-01 | B2: Reautorização do conector Google Ads v2.53 (prazo do Google) | C2: Google Ads | D2: 41 contas conectadas (43 fontes publicadas) | E2: R$ 101.708,91 em 30 dias (13/09–12/10) nas contas em reais com leitura confirmada, mais US$ 3.015,73 da Move | F2: Aviso do conector: prazo de 23/10/2026. O indicador de vencimento da Nekt ainda mostra "não vencido". | G2: Administrador do MCC reautoriza as fontes na interface da Nekt (usuário Google do MCC). | H2: Admin do MCC Google (nome a confirmar) | I2: 23/10 | J2: 22/10 | K2: P1 | L2: E1 | M2: Risco de a extração de Google Ads parar. O comportamento exato depois do prazo não foi testado.
A3: I-02 | B3: Meta: 7 contas com erro 403 (ads_read) | C3: Meta Ads | D3: 8 fontes (7 contas com 403 + 1 com 400) | E3: R$ 12.395,15 em 7 dias (13–19/10) nas contas visíveis no MCC: Shizen R$ 8.236,61, Farmabem R$ 3.045,47 e Santo Remédio Ecommerce R$ 1.113,07; BA Elétrica 2026 e CA 02 Arena estão fora do MCC; Santo Remédio Reserva Nova está desabilitada na Meta | F3: A conta não está atribuída ao usuário que autorizou a conexão (erro de conta, não de stream: confirmado por teste). Shizen: o e-mail do João de 15/10 diz que falta aprovação específica do cliente. | G3: Administrador do Business Manager atribui cada conta ao usuário da conexão (ou informa que a conta não deve ser mantida). | H3: João Araújo (admin Meta) | I3: 27/10 | J3: 20/10 | K3: P1 | L3: E1 | M3: Em 20/10 as cinco fontes ainda ativas falharam de novo. Em 21/10: xDLw, qy0W e bU6W com 3 falhas seguidas e ativas; geQA e tWIP com 2 (a de 27/10 chega a 3). KUkx e OJi6 (Shizen) estão INATIVAS desde 16/10: a conta de maior gasto sem leitura não é extraída até alguém reativar a fonte.
A4: I-03 | B4: Meta: 18 contas só com rascunho, sem autorização OAuth | C4: Meta Ads | D4: 18 | E4: R$ 25.081,20 em 7 dias (13–19/10), a maior lacuna de gasto da Meta. Maiores: AD - Apa Móveis Cliente R$ 6.979,58; Maravilha Motos (Honda Motos) R$ 4.442,39; CA01 - Comodare R$ 3.268,95; Carlos Oshiro R$ 1.942,53 | F4: Rascunho criado em 09/10 sem a autorização feita por quem administra cada conta. | G4: Autorizar o OAuth com o usuário que alcança a conta; depois confirmar o nome da camada (irreversível). | H4: João Araújo (admin Meta) + Jussara | I4: — | J4: OAuth 21/10 → publicar 22/10 → 1ª execução 27/10 | K4: P1 | L4: E2 | M4: O gasto dessas contas segue fora da base.
A5: I-04 | B5: Meta: CA Braga Motos 2, erro 400 no stream ads | C5: Meta Ads | D5: 1 | E5: R$ 1.404,57 em 7 dias | F5: Anúncio com asset_feed_spec em conflito com object_story_spec (código 100, subcódigo 2446211). | G5: Gestor de mídia corrige o anúncio na Meta; nova execução. | H5: Gestor de mídia da conta | I5: — | J5: 20/10 | K5: P2 | L5: E1 | M5: A conta continua sem leitura.
A6: I-05 | B6: Ex-clientes com fonte ainda publicada: Pátio Gourmet, Mari Mari e Olá Casa Nova | C6: Meta Ads / Google Ads | D6: 5 fontes Meta com 403 + FKfU + DzVL (Google) + 1 arquivada | E6: sem exposição de gasto na agência (clientes saíram); as fontes seguem rodando e falhando | F6: A Jussara informou em 16/10 que os três deixaram de ser clientes. As fontes seguem publicadas e vão falhar nas terças 20/10 e 27/10 até a Nekt desativá-las; as contas Google de Pátio Gourmet e Olá Casa Nova seguem no MCC. | G6: Arquivar as fontes na interface da Nekt (o MCP não arquiva); admin do MCC desvincula as contas Google. | H6: Jussara (arquivar) + Admin do MCC | I6: — | J6: 23/10 | K6: P3 | L6: E1 | M6: Falhas no histórico de execuções e crédito de agenda sem finalidade.
A7: I-06 | B7: Google: 4 contas bloqueadas (CDL, Santo Remédio antigo, Comac, Braga Venda Direta) | C7: Google Ads | D7: 4 | E7: CDL Manaus R$ 87,82 em 30 dias; as outras três não têm gasto visível (conta fora do MCC ou ID inexistente) | F7: CDL: o plano da conta inviabiliza rodar (informado pela Jussara em 16/10). Santo Remédio antigo (AMd2): conta saiu do MCC (403 CUSTOMER_NOT_ENABLED). Comac e Braga Venda Direta: IDs do mapeamento (306-130-0045 e 580-542-7544) não aparecem entre as contas do MCC. | G7: CDL: mudança de plano, sem previsão. AMd2: arquivar na interface. Comac e Braga Venda Direta: João confirma os IDs ou o vínculo. | H7: Conta CDL: AM/analista; demais: João Araújo (mapeamento) + Admin do MCC | I7: — | J7: 21/10 (IDs); CDL sem previsão | K7: P3 | L7: E1 | M7: Quatro contas sem possibilidade de leitura até a decisão.
A8: I-07 | B8: Google: 5 contas pendentes (4 aguardam autorização + conta própria da Vanguarda) | C8: Google Ads | D8: 5 | E8: R$ 2.497,66 em 30 dias. Maiores: AÇO MANAUS R$ 1.366,26; PNEU FORTE VAREJO R$ 768,29; TUBOAÇOS DA AMAZÔNIA R$ 174,46; VANGUARDA COMUNICAÇÃO (conta própria) R$ 161,26; BRAGA MOTORS BMW R$ 27,39 | F8: Aço Manaus, Braga Motors BMW, Pneu Forte Varejo e Tuboaços aguardam a autorização do cliente (informado pela Jussara em 16/10). A conta própria da Vanguarda (750-265-3880) não tem fonte e a decisão de entrar ainda não foi tomada. Ficaram de fora por decisão: Santo Remédio conta viva (e-mail do João de 30/09: não conectar por ora) e Dr. Cabral conta 2 (duplicidade). | G8: Autorização do cliente e OAuth com o usuário que administra o MCC; decisão sobre a conta própria. | H8: Account Managers + Admin do MCC | I8: — | J8: 21–23/10 | K8: P2 | L8: E2 | M8: 2,9% do gasto Google em reais (30 dias, contas aplicáveis) segue fora da base.
A9: I-08 | B9: Google: Prestex conectada em 16/10, mas em granularidade semanal e fora da Trusted | C9: Google Ads | D9: 1 | E9: R$ 11.285,82 em 30 dias (valor do MCC) | F9: Primeiro sucesso desde 08/09 em 16/10 09:28. Leitura confere com o MCC nas 4 semanas fechadas (R$ 10.958,01 dos dois lados), mas a tabela é SEMANAL e as outras 41 contas são diárias. | G9: Decidir se entra na união da Trusted de insight diário (somar semana e dia sem decisão misturaria granularidades). | H9: Jussara | I9: — | J9: 23/10 | K9: P3 | L9: E2 | M9: Fora da Trusted, o investimento da Prestex não aparece nos painéis.
A10: I-09 | B10: Google: 11 contas de ex-clientes e inativos ainda vinculadas ao MCC e gastando | C10: Google Ads | D10: 11 (Nova Era 5; UIARA; Pátio Gourmet 2; Olá Casa Nova; Hope Bay Park; Julia Herrera) | E10: R$ 46.430,03 em 30 dias (13/09–12/10); só a Nova Era é R$ 26.490,69 | F10: Nova Era saiu da agência em 05/10; Pátio Gourmet, Olá Casa Nova, UIARA, Hope Bay Park e Julia Herrera foram informados em 16/10 como ex-clientes ou inativos. O vínculo no MCC não foi desfeito. | G10: Administrador do MCC desvincula ou pausa as contas. | H10: Admin do MCC Google + Jussara | I10: — | J10: 23/10 | K10: P2 | L10: — | M10: Gasto sem contrato visível na agência.
A11: I-10 | B11: RD Station: 5 contas pendentes e CDL bloqueada | C11: RD Station | D11: 6 | E11: não aplicável (sem gasto) | F11: Targo, Legacy e Lovol sem conta RD confirmada; Braga Yamaha Vendas com rascunho sem OAuth; Braga Pós Venda a validar; CDL com 403 de plano. | G11: Analistas Inbound confirmam as contas e o administrador de cada RD autoriza. | H11: Analistas Inbound (Joyce, Juan Carlos, Bryan) | I11: — | J11: 21/10 | K11: P2 | L11: E2 | M11: Contatos e conversões dessas contas ficam fora.
A12: I-11 | B12: RD Station: duas fontes sem dado e três duplicatas | C12: RD Station | D12: 5 | E12: — | F12: Bajaj (tabelas de contatos e eventos não materializadas) e AMZ Imports (nenhuma tabela em mais de 34 execuções). Duplicatas: 1eaJ e bjQx são cópias da pDLk; CAA Alumínio e CAA Tintas são a mesma conta RD (2.125 de 2.125 contatos em comum). | G12: Investigar as duas sem dado; arquivar as duplicatas pela interface (o MCP não arquiva). | H12: Jussara + Analistas Inbound | I12: — | J12: 23/10 | K12: P3 | L12: E1 | M12: Crédito gasto sem dado novo (cerca de 65 por mês) e risco de contar a mesma conta duas vezes.
... A17: I-16 | B17: iClips: chave de API recusada (401); notebook inativo e duas fontes falhando | C17: iClips | D17: 3 pipelines | E17: não aplicável (sem gasto); afeta projetos, peças, apontamento e a Gold de tarefas | F17: A secret ICLIPS_API_KEY foi recusada como inválida, malformada ou expirada. O notebook-Rbpo falhou 3 vezes seguidas em 19/10 (13h, 17h, 21h) e a Nekt o desativou; sem execução desde então (conferido hoje). A rest-api-xk4P falhou em 20 e 21/10 (04:40) com o mesmo erro; a rest-api-73hk está com 3 falhas seguidas (último sucesso 28/09). | G17: Renovar a chave do iClips e atualizá-la na interface da Nekt (não passa pelo chat); só então reativar o notebook. | H17: Jussara (credencial) + dono do iClips | I17: — | J17: 22/10 | K17: P1 | L17: E1 | M17: As Trusted do iClips e a suíte de qualidade do iClips (53 regras) medem dado de 19/10 e vão envelhecendo.

Sheet Créditos por etapa
A1: Etapa | B1: O que entra | C1: Δ créditos/mês (regra "todas", agenda semanal) | D1: Δ créditos/mês (regra "qualquer" / diário) | E1: Como foi calculado | F1: Acumulado sem manuais | G1: % de 9.000 | H1: Acumulado com 300 manuais | I1: % de 9.000 | J1: Acumulado com 1.200 manuais (ritmo de outubro) | K1: % de 9.000 | L1: "Qualquer" + 300 manuais | M1: % de 9.000 | N1: "Qualquer" + 1.200 manuais | O1: % de 9.000
A2: E0 | B2: Linha de base: o que já está agendado hoje | C2: 0 | D2: 0 | E2: 7.601 execuções por mês; ~3.300 (43%) são o notebook do iClips a cada 4h e a cadeia que ele dispara | F2: 7601 | G2: 0.845 | H2: 7901 | I2: 0.878 | J2: 8801 | K2: 0.978 | L2: 7901 | M2: 0.878 | N2: 8801 | O2: 0.978
A3: E1 | B3: Desbloqueios (Meta 403, reautorização Google v2.53) | C3: 0 | D3: 0 | E3: as fontes já estão agendadas; falha não consome crédito | F3: 7601 | G3: 0.845 | H3: 7901 | I3: 0.878 | J3: 8801 | K3: 0.978 | L3: 7901 | M3: 0.878 | N3: 8801 | O3: 0.978
A4: E2 | B4: Publicar rascunhos: 18 Meta, 5 Google e 5 RD | C4: 122 | D4: 122 | E4: 28 fontes semanais novas | F4: 7723 | G4: 0.858 | H4: 8023 | I4: 0.891 | J4: 8923 | K4: 0.991 | L4: 8023 | M4: 0.891 | N4: 8923 | O4: 0.991
A5: E3 | B5: Somar as fontes Meta novas à Trusted de Facebook | C5: 4 | D5: 548 | E5: regra "todas" ≈ +4; regra "qualquer" ≈ +548 (63 fontes × 4,35 terças × 2 consultas) | F5: 7727 | G5: 0.859 | H5: 8027 | I5: 0.892 | J5: 8927 | K5: 0.992 | L5: 8571 | M5: 0.952 | N5: 9471 | O5: 1.052
A6: E4 | B6: TikTok e LinkedIn (7 contas) | C6: 30 | D6: 30 | E6: 7 fontes semanais | F6: 7757 | G6: 0.862 | H6: 8057 | I6: 0.895 | J6: 8957 | K6: 0.995 | L6: 8601 | M6: 0.956 | N6: 9501 | O6: 1.056
A7: E5 | B7: Agendar Instagram (11) e Páginas (14) | C7: 118 | D7: 761 | E7: semanal ≈ +118; diário ≈ +761 | F7: 7875 | G7: 0.875 | H7: 8175 | I7: 0.908 | J7: 9075 | K7: 1.008 | L7: 8719 | M7: 0.969 | N7: 9619 | O7: 1.069
A8: E6 | B8: Fonte de RH, Qulture e Quickin (se forem conectados) | C8: 13 | D8: 13 | E8: 3 fontes semanais; cadeia de tratamento não estimada | F8: 7888 | G8: 0.876 | H8: 8188 | I8: 0.91 | J8: 9088 | K8: 1.01 | L8: 8732 | M8: 0.97 | N8: 9632 | O8: 1.07
A10: Leitura: a coluna "Acumulado sem manuais" soma só o que está agendado. Execuções manuais são cobradas como as agendadas (cada passada da MySQL do VJOB custa cerca de 93; a do Google Ads, cerca de 97). 1 crédito = 1 execução bem-sucedida (regra oficial da Nekt). Falhas e cargas iniciais não são cobradas, então o modelo é ligeiramente conservador.
A11: Alavancas, em ordem de economia por mês: notebook do iClips de 4h para 8h ≈ 1.650; para 12h ≈ 2.200; para 1 por dia ≈ 2.750; RD diário para semanal ≈ 840; regra "todas" na Trusted de Facebook ≈ 544; duplicatas de RD ≈ 65. Cada uma é decisão de quem pediu a cadência atual.

Sheet Cronograma por etapa
A1: Etapa | B1: Nome | C1: Escopo | D1: Responsável (a confirmar) | E1: Depende de | F1: Prazo duro | G1: Conclusão estimada se destravado (proposta) | H1: Critério de saída
A2: E1 | B2: Desbloqueios | C2: Meta 403 (7) e 400 (1); reautorização v2.53 (41 contas, 43 fontes); conferir KL, AMZ Imports, Move CA2, Auto Master e manôa; renovar a chave do iClips (I-16) e reativar o notebook | D2: João Araújo (BM Meta); Admin do MCC Google (a confirmar); gestor de mídia; Jussara (chave do iClips) | E2: Atribuições e reautorização feitas | F2: 23/10 | G2: 28/10 | H2: Fontes em 403 sem erro na terça 27/10 e Google reautorizado extraindo
A3: E2 | B3: Publicar pendentes | C3: Meta 18; Google 5 (4 aguardam autorização + conta própria da Vanguarda); RD 5 | D3: João Araújo (BM Meta); Admin do MCC (a confirmar); AMs; analistas Inbound; Jussara (camadas) | E3: OAuth feito até 23/10; nomes de camada confirmados (irreversíveis) | F3: — | G3: 28/10 | H3: Primeira execução agendada (terça 27/10) com linhas na tabela de cada conta
A4: E3 | B4: Somar à Trusted | C4: 63 Meta já com dado (deploy 22/10); 18 Meta e Google novos depois; 19 RD novos | D4: Jussara | E4: Dado confirmado por conta; consulta com LIMIT 0 antes de publicar | F4: — | G4: 03/11 | H4: Contas novas presentes na Trusted e conferidas contra a plataforma
A5: E4 | B5: TikTok e LinkedIn | C5: 7 contas (TikTok 3, LinkedIn 4) | D5: João Araújo e analistas; admins das contas | E5: IDs levantados até 16/10 | F5: — | G5: 04/11 | H5: Primeira execução agendada com dado
A6: E5 | B6: Instagram e Páginas | C6: 108 fontes: agenda, lista de contas exigidas, limite de posts; somar as 48 novas às Trusted | D6: Gabriela Bezerra (Facebook e Instagram) + Jussara | E6: Decisão de escopo e cadência até 23/10 | F6: — | G6: 02/11 | H6: Lista de contas definida e cobertura calculável
A7: E6 | B7: Sistemas internos | C7: GitHub, Z-API, Semrush; RH, Qulture e Quickin se forem necessários | D7: Jussara; donos dos sistemas | E7: Configuração na interface de cada fonte | F7: — | G7: 30/10 (RH e demais sem data) | H7: Tabela com linhas em cada sistema
A8: E7 | B8: Fechamento | C8: Relatório de cobertura final com a mesma metodologia | D8: Jussara | E8: E1 a E6 | F8: — | G8: 04/11 | H8: Cobertura recalculada e entregue
B10: 100% das contas aplicáveis com leitura confirmada | C10: Estimativa: 04/11/2026, se TODAS as dependências externas forem entregues até 23/10. Cada semana de atraso no destravamento desloca a conclusão em uma semana (Meta e Google rodam às terças). Sem teto abaixo de 100%: Spotify e X ficaram sem conta aplicável e TikTok e LinkedIn têm conector. A CDL (bloqueada por plano) só chega lá se mudar de plano ou sair do denominador.

Sheet Validação do modelo
A1: Pipeline | B1: Cadência | C1: Execuções agendadas esperadas (01–15/10) | D1: Execuções com sucesso medidas | E1: Explicação da diferença
A2: supabase-x0tz | B2: diária 01:00 | C2: 15 | D2: 16 | E2: 1 disparo manual em 14/10
A3: query-GByA (depois da x0tz) | B3: diária ~03:30 | C3: 15 | D3: 16 | E3: 1 execução atrás do disparo manual
A4: mysql-yIOn | B4: domingo 00:00 | C4: 2 | D4: 5 | E4: 3 disparos manuais (06, 07 e 14/10)
A5: query-MZdN (depois do MySQL) | B5: evento | C5: 2 | D5: 5 | E5: segue cada execução do MySQL: 5 contra 5
A6: google-ads-cwt3 | B6: terça 13:43 | C6: 2 | D6: 4 | E6: 2 disparos manuais (06 e 07/10)
A7: rd-station-pDLk | B7: diária 12:20 | C7: 15 | D7: 17 | E7: 2 disparos manuais
A8: gmail-cF2Q | B8: diária 05:00 | C8: 15 | D8: 17 | E8: 2 disparos manuais
A9: linear-byrt | B9: diária 04:20 | C9: 15 | D9: 16 | E9: 1 disparo manual
A10: query-9dz7 (RD) | B10: diária 14:10 | C10: 14 | D10: 15 | E10: 1 disparo manual; a de 15/10 ainda não rodou
A11: facebook-ads-8RYU | B11: terça | C11: 0 | D11: 1 | E11: 1ª execução da fonte (carga inicial, que não é cobrada)
A12: query-8nEt (depois do notebook) | B12: evento | C12: 53 | D12: 53 | E12: segue cada sucesso do notebook: 53 contra 53
A13: notebook-Rbpo | B13: diária até 07/10; depois a cada 4h | C13: ≈55 | D13: 53 (+3 falhas) | E13: as 3 falhas de 13/10 não são cobradas; 4 disparos manuais
A15: Regra oficial (documentação da Nekt, 15/10): 1 crédito por execução bem-sucedida de fonte, consulta, notebook, histórico ou destino. Execução com falha, carga inicial de uma fonte e volume de linhas não são cobrados.
A16: Estimativa de consumo de 01 a 15/10: 3.100 a 3.750 agendados (o notebook custou menos na primeira semana, quando era diário) + cerca de 600 manuais = 3.700 a 4.400 créditos (41% a 49% do limite; o mês passou 48%). É uma estimativa: a tabela nekt_runs não está acessível ao token. Conferência definitiva em Workspace Settings › Billing.

Sheet Evidências
A1: Número | B1: Como foi medido | C1: Quando / valores | D1: Limite ou observação
A2: 209 contas aplicáveis | B2: Planilha oficial de contas de 16/10 (aba Contas), excluindo 13 da Nova Era, 2 duplicatas de RD e 18 de ex-clientes, inativos, duplicidade ou decisão de não conectar | C2: Inventário #1743 de 16/10 (242 linhas) | D2: Soma por plataforma: Meta 96, Google 50, RD 56, TikTok e LinkedIn 7
A3: Meta: 70 de 96 com leitura confirmada | B3: COUNT(*) e MAX(date_start) na tabela facebook_ads_adsinsights de cada uma das 64 camadas novas; Trusted consolidada para as 7 antigas | C3: 21/10 (leitura de hoje; 15/10 para as linhas por camada) | D3: Compara com o gasto de 13–19/10 lido no Graph da Meta em 21/10 (286 contas relidas, uma devolveu 403). Contagem de linhas e último dado medidos em 21/10 por COUNT(*) e MAX(date_start).
A4: Meta: 50 contas com gasto, todas dentro de 1% (68 em reais) | B4: SUM(spend) de 13–19/10 por camada contra o gasto de 7 dias da Meta para a mesma conta (leitura de 21/10) | C4: 21/10 | D4: Maior diferença R$ 6,06; totais R$ 72.067,79 (Nekt) e R$ 72.088,53 (Meta). Um lote de consulta devolveu resultados em posição trocada; 11 contas foram relidas uma a uma e a conferência cruzada com a Nekt não achou divergência acima de 1%
A5: Google: 41 de 50 com leitura confirmada | B5: trs_google_ads__insight_diario (MAX(data), SUM(investimento)) contra query_gaql por conta no MCC 1704439246; Prestex pela tabela semanal contra o MCC | C5: 21/10 (Nekt) e referência do MCC de 16/10 | D5: Referência de plataforma do Google NÃO relida em 21/10 (a ferramenta de consulta do MCC não estava conectada); vale a leitura de 16/10. A Nekt foi re-medida hoje. 85 contas no MCC em 15/10 (eram 88 em 05/10). Três contas Unipar ficam fora do MCC da Vanguarda e não têm referência independente
A6: Google: 34 contas em reais, 26 com gasto, todas dentro de 1% | B6: SUM(investimento) de 13/09–12/10 contra cost_micros por conta (comparação de 15/10, sem as contas que saíram do escopo) | C6: 21/10 (Nekt) contra MCC de 16/10 | D6: Maior diferença R$ 0,78; totais R$ 90.422,37 (Nekt, relida em 21/10) e R$ 90.423,09 (MCC de 16/10)
A7: Cobertura por gasto Meta 64,5% | B7: Gasto das contas com leitura confirmada ÷ gasto de todas as contas em reais do MCC da Meta, 13–19/10 | C7: R$ 72.088,53 ÷ R$ 111.727,79 (era 65,4% em 02–08/10) | D7: Contas em dólar e euro ficam de fora e não foram relidas hoje (16/10: US$ 679,32 em 7 dias). Inclui uma conta nova do MCC, 1675573549548233 (R$ 758,34), que não consta no inventário
A8: Cobertura por gasto Google 97,1% | B8: Idem, 13/09–12/10, sem as 5 contas Nova Era e sem as 6 contas de ex-clientes/inativos e as 2 contas de duplicidade e decisão | C8: R$ 101.708,91 ÷ R$ 104.743,53 | D8: O salto sobre os 71,2% de 15/10 (já em 16/10) vem do denominador; referência do MCC de 16/10. Com a Nova Era e os ex-clientes no denominador: 64,9% (denominador R$ 156.648,99)
A9: RD: 48 de 56 com dado presente | B9: Trusted de contatos e conversões por fonte (30 antigas) e COUNT(*) das 3 tabelas de cada fonte nova (19) | C9: 15/10 | D9: Conferência por amostra de 9 contagens do subagente contra o banco: 9 de 9 iguais
A10: CAA Alumínio e CAA Tintas são a mesma conta RD | B10: JOIN por uuid entre as duas tabelas de contatos | C10: 15/10 | D10: 2.125 contatos em comum de 2.125 em cada lado
A11: Instagram e Páginas | B11: COUNT(*) em 15 tabelas por fonte de Instagram e 8 de Páginas | C11: 15/10 | D11: Duas fontes de Páginas (PPsY, ftS8) sem camada identificada; camadas de IG e Páginas casadas pelo nome na descrição e conferidas por username/nome da página
A12: Sistemas internos | B12: COUNT(*) e MAX(_extraido_at) nas tabelas Trusted de cada sistema; execuções por list_pipeline_runs | C12: 15/10 | D12: GitHub e webhook Z-API re-medidos hoje: 0 linhas
... A16: Modelo de cadência validado | B16: list_pipeline_runs (01–15/10) em 12 pipelines contra a cadência esperada | C16: 15/10 | D16: Agendado bate em 11 pipelines e aproximadamente no notebook; o excedente são execuções manuais

Sheet Perguntas e respostas
A1: Pergunta provável | B1: Resposta
A2: Por que o saneamento é 100% e a cobertura não? | B2: São duas perguntas diferentes. O saneamento mede a qualidade do que já entrou (1.483 de 1.485 regras). A cobertura mede o que ainda não entrou: 76,1% das contas aplicáveis têm leitura confirmada. Um dado perfeito de três quartos das contas é uma base limpa e incompleta.
A3: Como vocês sabem que o dado da Nekt está certo? | B3: Comparamos a Nekt com a própria plataforma, conta a conta. Meta: 68 contas em reais comparadas (52 com gasto), todas dentro de 1%, maior diferença R$ 0,41, total R$ 64.652,99 na Nekt contra R$ 64.650,41 na Meta (0,004%). Google: 34 contas em reais (26 com gasto), todas dentro de 1%, maior diferença R$ 1,49, total R$ 90.426,30 contra R$ 90.423,09 (0,0035%); a Prestex entra à parte, em granularidade semanal (R$ 10.958,01 dos dois lados nas 4 semanas fechadas). Para o RD não existe referência independente; a validação é presença de dado.
A4: Conta sem veiculação conta como coberta? | B4: Conta com leitura confirmada em zero conta como coberta porque a Nekt e a plataforma dizem a mesma coisa (nada a ler). Mas separamos: "dado ativo" (62,7%) é a visão que exclui essas contas. A Diretoria pode usar qualquer das duas, desde que saiba qual.
A5: O que impede os 100%? | B5: Quatro coisas externas: atribuição das contas Meta no Business Manager, OAuth das 18 contas Meta pendentes, autorização do MCC Google (reautorização e contas novas) e IDs que faltam. Nenhuma se resolve pela Nekt. Não há mais teto abaixo de 100%: Spotify e X deixaram de ter conta aplicável (só havia Pátio Gourmet) e TikTok e LinkedIn têm conector.
A6: Por que as datas são "estimativas"? | B6: Porque dependem de pessoas fora da Nekt e da cadência semanal. Meta e Google rodam às terças; uma conta autorizada na quarta só entra na terça seguinte. Cada semana de atraso no destravamento desloca a conclusão em uma semana.
A7: Quando chegamos a 100% das contas aplicáveis? | B7: Em 04/11/2026, SE todas as dependências externas forem entregues até 23/10. É uma estimativa condicional, não um compromisso. Contas que a agência decidir não conectar (CDL por plano, por exemplo) precisam sair do denominador para o 100% ser alcançável.
A8: Os 9.000 créditos comportam o plano? | B8: Depende de três escolhas. Sem execuções manuais e com a regra de gatilho "todas" na Trusted de Facebook, o plano termina em 88% (7.888). Com 300 créditos manuais por mês fica em 91% (8.188). Com o ritmo manual de outubro (cerca de 1.200 por mês) passa de 100% (9.088, 101%). Com a regra "qualquer" no gatilho da Trusted de Facebook, o mesmo plano vai a 97% (8.732) com 300 manuais e a 107% (9.632) com o ritmo de outubro. MODELO DE 15/10, NÃO REFEITO EM 21/10: o notebook do iClips está inativo desde 19/10 (consumo corrente menor que o modelo) e as 48 fontes novas de Instagram e Páginas não entram na conta. Os números caíram em relação a 15/10 porque 8 contas saíram do plano (13 fontes a menos para publicar).
A9: Qual a base da conta de créditos? | B9: A regra oficial da Nekt: 1 crédito por execução bem-sucedida de fonte, consulta, notebook, histórico ou destino; execução com falha e a carga inicial de uma fonte não são cobradas; volume de linhas não entra. Testamos o modelo em 12 pipelines de 01 a 15/10: a cadência agendada bate exatamente em 11 e aproximadamente no notebook do iClips (mudou de cadência em 07/10; cerca de 55 esperadas, 53 com sucesso e 3 falhas não cobradas); o que passa do esperado são execuções manuais.
A10: Vocês mediram o consumo real do mês? | B10: Não. A tabela de metadados que registra o consumo (nekt_runs) não está acessível ao token usado. O consumo de 01 a 15/10 é estimado em 3.700 a 4.400 créditos (41% a 49%; o mês passou 48%). A conferência definitiva é em Workspace Settings › Billing.
A11: O que custa uma execução manual? | B11: A da MySQL do VJOB dispara a cadeia inteira: cerca de 93 créditos (1% do limite). A do Google Ads, cerca de 97. Em 01 a 15/10 foram identificadas 16 execuções manuais nas 12 fontes e consultas medidas, cerca de 600 créditos estimados.
A12: Por que Instagram e Páginas não têm percentual? | B12: Porque não existe lista de quais contas a agência exige; sem denominador, qualquer percentual seria inventado. O que está medido: 26 fontes criadas em 13–15/10, todas manuais, todas com sucesso, mas o Instagram traz de 0 a 9 posts de contas com 101 a 4.278.
... A14: O que não foi medido? | B14: Gasto de contas em dólar e euro fora do Google (Move) e Meta (2 contas); gasto da Meta em janela diferente de 02–08/10 (refeito em 21/10 só no lado Meta; a referência do Google segue sendo a de 16/10); cobertura do RD por referência independente; a causa da extração mínima do Instagram; as duas fontes de Páginas sem camada; o consumo real de créditos. Premissas minhas, ainda sem confirmação: Dr. Cabral conta 2 (4YJU) tratada como a duplicada; CDL tratada como bloqueada por plano; Santo Remédio antigo (AMd2) e as Meta f6h8 e geQA não foram abordadas e seguem como estavam.
