Workbook

Sheet Instruções
B1: Levantamento para a Camada Semântica
B2: VAN-SEM-001 | Versão 1.0 | Emissão 11/09/2026 | uso interno
B3: Plataforma de Dados Nekt — Vanguarda Martech
B5: O que é camada semântica | C5: É a documentação que diz O QUE O NÚMERO SIGNIFICA e COMO LÊ-LO SEM ERRAR. Não descreve como o trabalho é feito — descreve como o dado deve ser interpretado. Sem ela, cada relatório recalcula a métrica do seu jeito e dois times chegam a números diferentes para a mesma pergunta.
B6: O que este formulário NÃO é | C6: Não é mapeamento de processo. Não pede RACI, risco, competência, treinamento, retenção documental nem fluxo. Isso pertence ao SGQ e tem formulário próprio (VAN-FOR-SGQ-001).
B7: Quanto tempo leva | C7: Entre 20 e 40 minutos por setor. A maior parte já vem preenchida; você valida.
B8: As linhas azuis já vêm prontas | C8: São o que a plataforma de dados hoje sabe do seu setor: indicadores que já existem, armadilhas já medidas, tabelas que já rodam. CONFIRME, CORRIJA ou APAGUE. Se você discordar, a sua versão vale — você conhece o setor, eu conheço a tabela.
B9: Os três blocos | C9: 1) PERGUNTAS que você precisa responder com dado. É o que define o que a plataforma tem de servir; marcar 'Não' em 'Hoje consegue responder?' não é confissão de falha, é pedido de trabalho. 2) INDICADORES: nome, cálculo em palavras, unidade, recorte. 3) VOCABULÁRIO: o que cada termo significa no seu setor.
B10: A coluna mais importante | C10: 'O QUE NÃO VALE FAZER COM ELE', no bloco 2. É ela que evita o erro caro. Exemplos reais desta casa: não somar investimento entre moedas diferentes; não somar a coluna já arredondada; não usar o contador de atraso do VJOB como KPI enquanto a própria casa o classifica como inválido. Se você sabe de um jeito errado de ler um número seu, escreva ali — é a informação mais valiosa do formulário.
B11: Por que vocabulário importa tanto | C11: 'Job', 'verba', 'entrega' e 'cliente' significam coisas diferentes em Account, Mídia e Operações. Ninguém percebe até o número não bater numa reunião. Escrever a definição custa dois minutos e evita a discussão inteira.
B12: Cores | C12: Azul-claro = já preenchido, para validar. Amarelo = campo seu, em branco. Verde = calculado, não digite. Cinza claro = coluna não usada naquele bloco.
B13: O que acontece depois | C13: Cada aba devolvida vira um documento de contexto na camada semântica da Nekt, com as fórmulas e as regras de leitura que você declarou. A partir daí, toda consulta — feita por pessoa ou por IA — passa a enxergar a sua definição antes de calcular.
B14: Devolução | C14: Devolver a planilha inteira, com todas as abas. A aba Consolidado mostra sozinha quem já concluiu.

Sheet Mídia Paga
A1: Camada Semântica — Mídia Paga
A2: VAN-SEM-001 | Versão 1.0 | Emissão 11/09/2026 | Plataforma de Dados Nekt | uso interno
A3: Objetivo: registrar o que o número significa neste setor e como lê-lo sem errar. Não é mapeamento de processo.
A5: COMO PREENCHER: as linhas em azul-claro já vêm preenchidas com o que a plataforma de dados hoje sabe deste setor — sua tarefa é CONFIRMAR ou CORRIGIR, e acrescentar o que falta nas linhas em branco. Se discordar de uma linha pré-preenchida, sobrescreva: a sua versão vale mais que a minha.
A7: FICHA DO SETOR
A8: Quem responde por este preenchimento
A9: Cargo / função
A10: Sistemas que o setor usa no dia a dia
A11: Com que frequência o setor decide com dado
A12: Período que costuma olhar (ex.: mês corrente, últimos 90 dias)
A14: 1. PERGUNTAS QUE O SETOR PRECISA RESPONDER COM DADO — define o que a camada Refined tem de servir
A15: Pergunta | B15: Decisão que depende dela | C15: Frequência | D15: Hoje consegue responder? | E15: Onde busca hoje | G15: Origem da linha
A16: Quanto cada cliente investiu no período, por plataforma? | B16: Realocação de verba entre contas | C16: Semanal | E16: rfn_midia__desempenho_diario | G16: pré-preenchido — confirme ou corrija
A17: Quais campanhas estão sem entrega e há quantos dias? | B17: Pausar ou reativar campanha | C17: Semanal | E17: rfn_midia__desempenho_diario | G17: pré-preenchido — confirme ou corrija
A18: Qual o custo por conversão por conta e por canal? | B18: Ajuste de lance e de canal | C18: Semanal | E18: rfn_midia__desempenho_diario | G18: pré-preenchido — confirme ou corrija
A30: 2. INDICADORES — nome, cálculo e, sobretudo, o que NÃO vale fazer com ele
A31: Indicador | B31: Como se calcula (em palavras) | C31: Unidade | D31: Recorte habitual | E31: O que NÃO vale fazer com ele | F31: Dono da definição | G31: Origem da linha
A32: Investimento | B32: Somar investimento_micros e dividir por 1.000.000 | C32: R$ ou US$ | D32: Conta, campanha, dia | E32: NÃO somar a coluna investimento (é arredondada por linha: acumulou R$ 0,90 em 42 mil linhas). NÃO somar BRL com USD. | G32: pré-preenchido — confirme ou corrija
A33: Cobertura demográfica | B33: Verba não-PMax ÷ verba total | C33: % | D33: Conta | E33: NÃO usar as tabelas de faixa etária/gênero para totalizar verba: PERFORMANCE_MAX não publica breakdown demográfico. | G33: pré-preenchido — confirme ou corrija
A34: Cobertura de termo de busca | B34: Verba com termo publicado ÷ verba de SEARCH+SHOPPING | C34: % | D34: Conta | E34: NÃO usar a verba total como denominador: DISPLAY, VIDEO e PMax não têm termo de busca para publicar. | G34: pré-preenchido — confirme ou corrija
A35: Conta defasada | B35: Dias desde a última data com entrega | C35: dias | D35: Conta | E35: NÃO ler como fonte parada: em 11 de 36 contas a extração rodou e teve sucesso — a conta é que parou de anunciar. | G35: pré-preenchido — confirme ou corrija
A51: 3. VOCABULÁRIO DO SETOR — o bloco mais barato e o de maior retorno
A52: Termo | B52: O que significa NESTE setor | E52: Onde aparece no dado | G52: Origem da linha
A53: Verba | B53: Investimento veiculado na plataforma de mídia, em micros na origem | E53: rfn_midia__desempenho_diario.investimento_micros | G53: pré-preenchido — confirme ou corrija
A54: Conta | B54: Unidade de cobrança da plataforma. Contas de nome parecido NÃO se fundem (R-003). | E54: id_conta | G54: pré-preenchido — confirme ou corrija
A55: PMax | B55: Campanha PERFORMANCE_MAX: não publica desempenho por anúncio nem breakdown demográfico | E55: canal / subcanal | G55: pré-preenchido — confirme ou corrija
A56: Grão misto | B56: Linha de anúncio somada a linha de campanha só onde não há anúncio | E56: grao_origem | G56: pré-preenchido — confirme ou corrija

Sheet Inbound
A1: Camada Semântica — Inbound
A2: VAN-SEM-001 | Versão 1.0 | Emissão 11/09/2026 | Plataforma de Dados Nekt | uso interno
A3: Objetivo: registrar o que o número significa neste setor e como lê-lo sem errar. Não é mapeamento de processo.
A5: COMO PREENCHER: as linhas em azul-claro já vêm preenchidas com o que a plataforma de dados hoje sabe deste setor — sua tarefa é CONFIRMAR ou CORRIGIR, e acrescentar o que falta nas linhas em branco. Se discordar de uma linha pré-preenchida, sobrescreva: a sua versão vale mais que a minha.
A7: FICHA DO SETOR
A8: Quem responde por este preenchimento
A9: Cargo / função
A10: Sistemas que o setor usa no dia a dia
A11: Com que frequência o setor decide com dado
A12: Período que costuma olhar (ex.: mês corrente, últimos 90 dias)
A14: 1. PERGUNTAS QUE O SETOR PRECISA RESPONDER COM DADO — define o que a camada Refined tem de servir
A15: Pergunta | B15: Decisão que depende dela | C15: Frequência | D15: Hoje consegue responder? | E15: Onde busca hoje | G15: Origem da linha
A16: Quantas conversões vieram de cada origem de tráfego? | B16: Onde concentrar esforço de geração | C16: Semanal | E16: rfn_marketing__conversao | G16: pré-preenchido — confirme ou corrija
A17: Que parcela das conversões liga a uma campanha de Google Ads? | B17: Atribuição de investimento a resultado | C17: Mensal | E17: rfn_marketing__conversao | G17: pré-preenchido — confirme ou corrija
A30: 2. INDICADORES — nome, cálculo e, sobretudo, o que NÃO vale fazer com ele
A31: Indicador | B31: Como se calcula (em palavras) | C31: Unidade | D31: Recorte habitual | E31: O que NÃO vale fazer com ele | F31: Dono da definição | G31: Origem da linha
A32: Conversões por origem | B32: Contar id_conversao agrupando por origem_canonica | C32: un. | D32: Cliente, canal, mês | E32: NÃO ler só utm_source: ele traz 1.400 linhas com um único valor distinto e dá a falsa impressão de que não há origem. | G32: pré-preenchido — confirme ou corrija
A33: Cobertura de funil | B33: Conversões com gad_campaignid ÷ total de conversões | C33: % | D33: Cliente | E33: Cobertura baixa (5,2%, 908 de 17.602) é o número certo, não erro. NÃO casar por nome de cliente para 'melhorar': só 8 rótulos batem e a R-003 proíbe fundir os casos 3-para-1. | G33: pré-preenchido — confirme ou corrija
A51: 3. VOCABULÁRIO DO SETOR — o bloco mais barato e o de maior retorno
A52: Termo | B52: O que significa NESTE setor | E52: Onde aparece no dado | G52: Origem da linha
A53: Origem canônica | B53: Origem de tráfego já decodificada dos 5 formatos brutos | E53: origem_canonica | G53: pré-preenchido — confirme ou corrija
A54: Conversão | B54: Um evento de contato do RD Station | E54: id_conversao | G54: pré-preenchido — confirme ou corrija
A55: Canal pago | B55: Marcação booleana de origem paga | E55: canal_pago | G55: pré-preenchido — confirme ou corrija

Sheet Account
A1: Camada Semântica — Account (Atendimento)
A2: VAN-SEM-001 | Versão 1.0 | Emissão 11/09/2026 | Plataforma de Dados Nekt | uso interno
A3: Objetivo: registrar o que o número significa neste setor e como lê-lo sem errar. Não é mapeamento de processo.
A5: COMO PREENCHER: as linhas em azul-claro já vêm preenchidas com o que a plataforma de dados hoje sabe deste setor — sua tarefa é CONFIRMAR ou CORRIGIR, e acrescentar o que falta nas linhas em branco. Se discordar de uma linha pré-preenchida, sobrescreva: a sua versão vale mais que a minha.
A7: FICHA DO SETOR
A8: Quem responde por este preenchimento
A9: Cargo / função
A10: Sistemas que o setor usa no dia a dia
A11: Com que frequência o setor decide com dado
A12: Período que costuma olhar (ex.: mês corrente, últimos 90 dias)
A14: 1. PERGUNTAS QUE O SETOR PRECISA RESPONDER COM DADO — define o que a camada Refined tem de servir
A15: Pergunta | B15: Decisão que depende dela | C15: Frequência | D15: Hoje consegue responder? | E15: Onde busca hoje | G15: Origem da linha
A16: Qual o volume de jobs por cliente e em que etapa estão? | B16: Priorização e alerta de prazo | C16: Semanal | E16: iClips — fato_atividade | G16: pré-preenchido — confirme ou corrija
A17: Qual o faturamento por cliente e o que está por faturar? | B17: Conversa comercial e cobrança | C17: Mensal | E17: Conta Azul — vw_funil_faturamento | G17: pré-preenchido — confirme ou corrija
A30: 2. INDICADORES — nome, cálculo e, sobretudo, o que NÃO vale fazer com ele
A31: Indicador | B31: Como se calcula (em palavras) | C31: Unidade | D31: Recorte habitual | E31: O que NÃO vale fazer com ele | F31: Dono da definição | G31: Origem da linha
A32: Jobs por cliente | B32: Contar job_id distintos por client_name | C32: un. | D32: Cliente, mês | E32: NÃO usar client_name para agrupar grupo econômico — use client_group_name ou CNPJ. | G32: pré-preenchido — confirme ou corrija
A33: Valor faturado | B33: Somar valor_faturado_cliente | C33: R$ | D33: Cliente, competência | E33: Para BRUTO × LÍQUIDO use tipo_faturamento (fonte autoritativa do ERP), não a inferência por CNPJ da nota. | G33: pré-preenchido — confirme ou corrija
A51: 3. VOCABULÁRIO DO SETOR — o bloco mais barato e o de maior retorno
A52: Termo | B52: O que significa NESTE setor | E52: Onde aparece no dado | G52: Origem da linha
A53: PI | B53: Pedido de Inserção — o contrato de veiculação de mídia | E53: silver_pi_insercao.pi | G53: pré-preenchido — confirme ou corrija
A54: Job | B54: Unidade de trabalho da agência | E54: fato_atividade.job_id | G54: pré-preenchido — confirme ou corrija
A55: Grupo econômico | B55: Conjunto de clientes do mesmo dono, com CNPJs distintos | E55: client_group_name / tags_id | G55: pré-preenchido — confirme ou corrija

Sheet Criação
A1: Camada Semântica — Criação
A2: VAN-SEM-001 | Versão 1.0 | Emissão 11/09/2026 | Plataforma de Dados Nekt | uso interno
A3: Objetivo: registrar o que o número significa neste setor e como lê-lo sem errar. Não é mapeamento de processo.
A5: COMO PREENCHER: as linhas em azul-claro já vêm preenchidas com o que a plataforma de dados hoje sabe deste setor — sua tarefa é CONFIRMAR ou CORRIGIR, e acrescentar o que falta nas linhas em branco. Se discordar de uma linha pré-preenchida, sobrescreva: a sua versão vale mais que a minha.
A7: FICHA DO SETOR
A8: Quem responde por este preenchimento
A9: Cargo / função
A10: Sistemas que o setor usa no dia a dia
A11: Com que frequência o setor decide com dado
A12: Período que costuma olhar (ex.: mês corrente, últimos 90 dias)
A14: 1. PERGUNTAS QUE O SETOR PRECISA RESPONDER COM DADO — define o que a camada Refined tem de servir
A15: Pergunta | B15: Decisão que depende dela | C15: Frequência | D15: Hoje consegue responder? | E15: Onde busca hoje | G15: Origem da linha
A16: Quantas peças foram entregues por etapa de workflow? | B16: Dimensionamento de equipe | C16: Semanal | E16: iClips — fato_atividade | G16: pré-preenchido — confirme ou corrija
A17: Qual o índice de refação e onde ele se concentra? | B17: Ajuste de briefing e de processo | C17: Mensal | E17: iClips — fato_atividade | G17: pré-preenchido — confirme ou corrija
A30: 2. INDICADORES — nome, cálculo e, sobretudo, o que NÃO vale fazer com ele
A31: Indicador | B31: Como se calcula (em palavras) | C31: Unidade | D31: Recorte habitual | E31: O que NÃO vale fazer com ele | F31: Dono da definição | G31: Origem da linha
A32: Peças por etapa | B32: Contar piece_id por workflow_normalizado | C32: un. | D32: Cliente, mês, responsável | E32: NÃO agrupar pela coluna workflow crua: grafias mistas fragmentaram 29.765 atividades (VAN-73). Use workflow_normalizado. | G32: pré-preenchido — confirme ou corrija
A33: Índice de refação | B33: Peças com refacao ÷ total de peças | C33: % | D33: Cliente, responsável | E33: Confirmar com a equipe o que conta como refação antes de publicar o indicador. | G33: pré-preenchido — confirme ou corrija
A51: 3. VOCABULÁRIO DO SETOR — o bloco mais barato e o de maior retorno
A52: Termo | B52: O que significa NESTE setor | E52: Onde aparece no dado | G52: Origem da linha
A53: Peça | B53: Entregável individual dentro de um job | E53: fato_atividade.piece_id | G53: pré-preenchido — confirme ou corrija
A54: Workflow | B54: Etapa do fluxo da peça — é o nome da etapa, não do template | E54: workflow_normalizado | G54: pré-preenchido — confirme ou corrija
A55: Refação | B55: Retrabalho de peça já entregue | E55: fato_atividade.refacao | G55: pré-preenchido — confirme ou corrija

Sheet Direção de Arte
A1: Camada Semântica — Direção de Arte
A2: VAN-SEM-001 | Versão 1.0 | Emissão 11/09/2026 | Plataforma de Dados Nekt | uso interno
A3: Objetivo: registrar o que o número significa neste setor e como lê-lo sem errar. Não é mapeamento de processo.
A5: COMO PREENCHER: as linhas em azul-claro já vêm preenchidas com o que a plataforma de dados hoje sabe deste setor — sua tarefa é CONFIRMAR ou CORRIGIR, e acrescentar o que falta nas linhas em branco. Se discordar de uma linha pré-preenchida, sobrescreva: a sua versão vale mais que a minha.
A7: FICHA DO SETOR
A8: Quem responde por este preenchimento
A9: Cargo / função
A10: Sistemas que o setor usa no dia a dia
A11: Com que frequência o setor decide com dado
A12: Período que costuma olhar (ex.: mês corrente, últimos 90 dias)
A14: 1. PERGUNTAS QUE O SETOR PRECISA RESPONDER COM DADO — define o que a camada Refined tem de servir
A15: Pergunta | B15: Decisão que depende dela | C15: Frequência | D15: Hoje consegue responder? | E15: Onde busca hoje | G15: Origem da linha
A16: Qual o tempo médio entre entrada e aprovação da peça? | B16: Negociação de prazo com Account | C16: Mensal | E16: iClips — fato_atividade | G16: pré-preenchido — confirme ou corrija
A30: 2. INDICADORES — nome, cálculo e, sobretudo, o que NÃO vale fazer com ele
A31: Indicador | B31: Como se calcula (em palavras) | C31: Unidade | D31: Recorte habitual | E31: O que NÃO vale fazer com ele | F31: Dono da definição | G31: Origem da linha
A32: Tempo de ciclo da peça | B32: data_fim_peca_workflow menos data_inicio_peca_workflow | C32: dias | D32: Cliente, tipo de peça | E32: Conferir se estimated_time e sla_time estão preenchidos: linha sem eles não entra na média e enviesa o resultado. | G32: pré-preenchido — confirme ou corrija
A51: 3. VOCABULÁRIO DO SETOR — o bloco mais barato e o de maior retorno
A52: Termo | B52: O que significa NESTE setor | E52: Onde aparece no dado | G52: Origem da linha
A53: Aprovação | B53: Marco em que a peça é aceita pelo cliente | E53: project_approval_date | G53: pré-preenchido — confirme ou corrija

Sheet Dir. Operações
A1: Camada Semântica — Diretoria de Operações
A2: VAN-SEM-001 | Versão 1.0 | Emissão 11/09/2026 | Plataforma de Dados Nekt | uso interno
A3: Objetivo: registrar o que o número significa neste setor e como lê-lo sem errar. Não é mapeamento de processo.
A5: COMO PREENCHER: as linhas em azul-claro já vêm preenchidas com o que a plataforma de dados hoje sabe deste setor — sua tarefa é CONFIRMAR ou CORRIGIR, e acrescentar o que falta nas linhas em branco. Se discordar de uma linha pré-preenchida, sobrescreva: a sua versão vale mais que a minha.
A7: FICHA DO SETOR
A8: Quem responde por este preenchimento
A9: Cargo / função
A10: Sistemas que o setor usa no dia a dia
A11: Com que frequência o setor decide com dado
A12: Período que costuma olhar (ex.: mês corrente, últimos 90 dias)
A14: 1. PERGUNTAS QUE O SETOR PRECISA RESPONDER COM DADO — define o que a camada Refined tem de servir
A15: Pergunta | B15: Decisão que depende dela | C15: Frequência | D15: Hoje consegue responder? | E15: Onde busca hoje | G15: Origem da linha
A16: Quantos jobs estão abertos, por responsável e por prazo? | B16: Redistribuição de carga | C16: Semanal | E16: rfn_operacao__job (VJOB) | G16: pré-preenchido — confirme ou corrija
A30: 2. INDICADORES — nome, cálculo e, sobretudo, o que NÃO vale fazer com ele
A31: Indicador | B31: Como se calcula (em palavras) | C31: Unidade | D31: Recorte habitual | E31: O que NÃO vale fazer com ele | F31: Dono da definição | G31: Origem da linha
A32: Jobs em aberto | B32: Contar jobs com status diferente de concluído | C32: un. | D32: Responsável, cliente | E32: O CONTADOR DE ATRASO DO VJOB ESTÁ FORMALMENTE CLASSIFICADO COMO INVÁLIDO pela própria casa enquanto o saneamento de prazos não conclui. NÃO usar como KPI. | G32: pré-preenchido — confirme ou corrija
A51: 3. VOCABULÁRIO DO SETOR — o bloco mais barato e o de maior retorno
A52: Termo | B52: O que significa NESTE setor | E52: Onde aparece no dado | G52: Origem da linha
A53: Job | B53: Tarefa corporativa registrada no VJOB | E53: rfn_operacao__job | G53: pré-preenchido — confirme ou corrija
A54: Prazo inconsistente | B54: Tarefa com prazo anterior à própria publicação | E54: marca do PMO | G54: pré-preenchido — confirme ou corrija

Sheet RH
A1: Camada Semântica — Recursos Humanos
A2: VAN-SEM-001 | Versão 1.0 | Emissão 11/09/2026 | Plataforma de Dados Nekt | uso interno
A3: Objetivo: registrar o que o número significa neste setor e como lê-lo sem errar. Não é mapeamento de processo.
A5: COMO PREENCHER: as linhas em azul-claro já vêm preenchidas com o que a plataforma de dados hoje sabe deste setor — sua tarefa é CONFIRMAR ou CORRIGIR, e acrescentar o que falta nas linhas em branco. Se discordar de uma linha pré-preenchida, sobrescreva: a sua versão vale mais que a minha.
A7: FICHA DO SETOR
A8: Quem responde por este preenchimento
A9: Cargo / função
A10: Sistemas que o setor usa no dia a dia
A11: Com que frequência o setor decide com dado
A12: Período que costuma olhar (ex.: mês corrente, últimos 90 dias)
A14: 1. PERGUNTAS QUE O SETOR PRECISA RESPONDER COM DADO — define o que a camada Refined tem de servir
A15: Pergunta | B15: Decisão que depende dela | C15: Frequência | D15: Hoje consegue responder? | E15: Onde busca hoje | G15: Origem da linha
A16: Qual o turnover do período e onde ele se concentra? | B16: Ação de retenção por área | C16: Mensal | E16: silver_colaborador_rel | G16: pré-preenchido — confirme ou corrija
A17: Qual o tempo médio de casa por área? | B17: Plano de carreira e sucessão | C17: Trimestral | E17: silver_colaborador_rel | G17: pré-preenchido — confirme ou corrija
A30: 2. INDICADORES — nome, cálculo e, sobretudo, o que NÃO vale fazer com ele
A31: Indicador | B31: Como se calcula (em palavras) | C31: Unidade | D31: Recorte habitual | E31: O que NÃO vale fazer com ele | F31: Dono da definição | G31: Origem da linha
A32: Turnover | B32: Desligamentos no período ÷ headcount médio | C32: % | D32: Área, departamento, nível | E32: NÃO usar data_desligamento crua em série: use data_desligamento_efetiva. A crua guarda resíduo de vínculo antigo em recontratação. | G32: pré-preenchido — confirme ou corrija
A33: Headcount | B33: Contar pessoas com situacao = ATIVO | C33: un. | D33: Área, departamento | E33: Tratar ATIVO_INCONSISTENTE à parte: é cadastro a corrigir na origem, não uma categoria de pessoa. | G33: pré-preenchido — confirme ou corrija
A51: 3. VOCABULÁRIO DO SETOR — o bloco mais barato e o de maior retorno
A52: Termo | B52: O que significa NESTE setor | E52: Onde aparece no dado | G52: Origem da linha
A53: Situação | B53: Estado do vínculo: ATIVO, AVISO_PREVIO, DESLIGADO ou ATIVO_INCONSISTENTE | E53: colaborador_rel.situacao | G53: pré-preenchido — confirme ou corrija
A54: Tempo de casa | B54: Meses entre admissão e hoje, ou até o desligamento efetivo | E54: tempo_casa_meses | G54: pré-preenchido — confirme ou corrija

Sheet Dir. Executiva
A1: Camada Semântica — Diretoria Executiva
A2: VAN-SEM-001 | Versão 1.0 | Emissão 11/09/2026 | Plataforma de Dados Nekt | uso interno
A3: Objetivo: registrar o que o número significa neste setor e como lê-lo sem errar. Não é mapeamento de processo.
A5: COMO PREENCHER: as linhas em azul-claro já vêm preenchidas com o que a plataforma de dados hoje sabe deste setor — sua tarefa é CONFIRMAR ou CORRIGIR, e acrescentar o que falta nas linhas em branco. Se discordar de uma linha pré-preenchida, sobrescreva: a sua versão vale mais que a minha.
A7: FICHA DO SETOR
A8: Quem responde por este preenchimento
A9: Cargo / função
A10: Sistemas que o setor usa no dia a dia
A11: Com que frequência o setor decide com dado
A12: Período que costuma olhar (ex.: mês corrente, últimos 90 dias)
A14: 1. PERGUNTAS QUE O SETOR PRECISA RESPONDER COM DADO — define o que a camada Refined tem de servir
A15: Pergunta | B15: Decisão que depende dela | C15: Frequência | D15: Hoje consegue responder? | E15: Onde busca hoje | G15: Origem da linha
A16: Qual a receita por cliente e por linha de serviço? | B16: Decisão de portfólio | C16: Mensal | E16: gold_vw_fin_cliente | G16: pré-preenchido — confirme ou corrija
A17: Qual o caixa realizado contra o projetado? | B17: Decisão de investimento | C17: Mensal | E17: gold_vw_fato_dfc_dia | G17: pré-preenchido — confirme ou corrija
A30: 2. INDICADORES — nome, cálculo e, sobretudo, o que NÃO vale fazer com ele
A31: Indicador | B31: Como se calcula (em palavras) | C31: Unidade | D31: Recorte habitual | E31: O que NÃO vale fazer com ele | F31: Dono da definição | G31: Origem da linha
A32: Receita por cliente | B32: Somar valor agrupando por cliente_key | C32: R$ | D32: Cliente, grupo, linha de serviço | E32: SEMPRE separar por flag_projecao: misturar realizado com projeção produz número que não existe. | G32: pré-preenchido — confirme ou corrija
A33: MRR | B33: Somar mrr do mês | C33: R$ | D33: Cliente, produto, família | E33: Distinguir tipo = plano de tipo = serviço: são chaves de produto diferentes (ORI-603). | G33: pré-preenchido — confirme ou corrija
A51: 3. VOCABULÁRIO DO SETOR — o bloco mais barato e o de maior retorno
A52: Termo | B52: O que significa NESTE setor | E52: Onde aparece no dado | G52: Origem da linha
A53: Realizado × Projetado | B53: Separação obrigatória em toda leitura financeira | E53: flag_projecao | G53: pré-preenchido — confirme ou corrija
A54: Grupo | B54: Agrupamento econômico acima do cliente | E54: grupo_key / grupo_nome | G54: pré-preenchido — confirme ou corrija

Sheet Social Media
A1: Camada Semântica — Social Media
A2: VAN-SEM-001 | Versão 1.0 | Emissão 11/09/2026 | Plataforma de Dados Nekt | uso interno
A3: Objetivo: registrar o que o número significa neste setor e como lê-lo sem errar. Não é mapeamento de processo.
A5: COMO PREENCHER: as linhas em azul-claro já vêm preenchidas com o que a plataforma de dados hoje sabe deste setor — sua tarefa é CONFIRMAR ou CORRIGIR, e acrescentar o que falta nas linhas em branco. Se discordar de uma linha pré-preenchida, sobrescreva: a sua versão vale mais que a minha.
A7: FICHA DO SETOR
A8: Quem responde por este preenchimento
A9: Cargo / função
A10: Sistemas que o setor usa no dia a dia
A11: Com que frequência o setor decide com dado
A12: Período que costuma olhar (ex.: mês corrente, últimos 90 dias)
A14: 1. PERGUNTAS QUE O SETOR PRECISA RESPONDER COM DADO — define o que a camada Refined tem de servir
A15: Pergunta | B15: Decisão que depende dela | C15: Frequência | D15: Hoje consegue responder? | E15: Onde busca hoje | G15: Origem da linha
A16: Quantas peças de social foram publicadas por cliente? | B16: Cumprimento de contrato | C16: Mensal | E16: iClips — fato_atividade | G16: pré-preenchido — confirme ou corrija
A30: 2. INDICADORES — nome, cálculo e, sobretudo, o que NÃO vale fazer com ele
A31: Indicador | B31: Como se calcula (em palavras) | C31: Unidade | D31: Recorte habitual | E31: O que NÃO vale fazer com ele | F31: Dono da definição | G31: Origem da linha
A32: Peças publicadas | B32: Contar peças com prefixo [SOCIAL MEDIA] no catálogo | C32: un. | D32: Cliente, mês | E32: Separar peça produzida de peça veiculada: são coisas diferentes e o dado hoje registra a produção. | G32: pré-preenchido — confirme ou corrija
A51: 3. VOCABULÁRIO DO SETOR — o bloco mais barato e o de maior retorno
A52: Termo | B52: O que significa NESTE setor | E52: Onde aparece no dado | G52: Origem da linha
A53: Peça de social | B53: Entregável do catálogo com prefixo [SOCIAL MEDIA] | E53: dim_peca_canonica.prefixo | G53: pré-preenchido — confirme ou corrija

Sheet Financeiro
A1: Camada Semântica — Financeiro / Controladoria
A2: VAN-SEM-001 | Versão 1.0 | Emissão 11/09/2026 | Plataforma de Dados Nekt | uso interno
A3: Objetivo: registrar o que o número significa neste setor e como lê-lo sem errar. Não é mapeamento de processo.
A5: COMO PREENCHER: as linhas em azul-claro já vêm preenchidas com o que a plataforma de dados hoje sabe deste setor — sua tarefa é CONFIRMAR ou CORRIGIR, e acrescentar o que falta nas linhas em branco. Se discordar de uma linha pré-preenchida, sobrescreva: a sua versão vale mais que a minha.
A7: FICHA DO SETOR
A8: Quem responde por este preenchimento
A9: Cargo / função
A10: Sistemas que o setor usa no dia a dia
A11: Com que frequência o setor decide com dado
A12: Período que costuma olhar (ex.: mês corrente, últimos 90 dias)
A14: 1. PERGUNTAS QUE O SETOR PRECISA RESPONDER COM DADO — define o que a camada Refined tem de servir
A15: Pergunta | B15: Decisão que depende dela | C15: Frequência | D15: Hoje consegue responder? | E15: Onde busca hoje | G15: Origem da linha
A16: Qual a inadimplência por cliente e por faixa de atraso? | B16: Régua de cobrança | C16: Semanal | E16: vw_inad_titulos_vbot | G16: pré-preenchido — confirme ou corrija
A17: Qual o fluxo de caixa diário por conta? | B17: Programação de pagamento | C17: Diária | E17: vw_fluxo_caixa_diario | G17: pré-preenchido — confirme ou corrija
A30: 2. INDICADORES — nome, cálculo e, sobretudo, o que NÃO vale fazer com ele
A31: Indicador | B31: Como se calcula (em palavras) | C31: Unidade | D31: Recorte habitual | E31: O que NÃO vale fazer com ele | F31: Dono da definição | G31: Origem da linha
A32: Inadimplência | B32: Somar valor_aberto de títulos vencidos | C32: R$ | D32: Cliente, faixa de atraso | E32: Títulos com flag_migrado vieram do iClips em 01/06/2026 e a baixa ocorre no Conta Azul — não contar cobrança em dobro. | G32: pré-preenchido — confirme ou corrija
A33: Perda (write-off) | B33: Somar o campo perda | C33: R$ | D33: Cliente, período | E33: A API devolve perda como objeto {data, valor}, não escalar — ler perda.valor, senão o total sai zerado. | G33: pré-preenchido — confirme ou corrija
A51: 3. VOCABULÁRIO DO SETOR — o bloco mais barato e o de maior retorno
A52: Termo | B52: O que significa NESTE setor | E52: Onde aparece no dado | G52: Origem da linha
A53: Parcela | B53: Unidade de cobrança do evento financeiro | E53: ca_fato_evento_financeiro.id_parcela | G53: pré-preenchido — confirme ou corrija
A54: Baixa | B54: Registro de pagamento da parcela | E54: campo baixas | G54: pré-preenchido — confirme ou corrija
A55: Conciliado | B55: Parcela batida com o extrato | E55: conciliado | G55: pré-preenchido — confirme ou corrija

Sheet Planej. Estrat. e Inovação
A1: Camada Semântica — Planejamento, Estratégia e Inovação
A2: VAN-SEM-001 | Versão 1.0 | Emissão 11/09/2026 | Plataforma de Dados Nekt | uso interno
A3: Objetivo: registrar o que o número significa neste setor e como lê-lo sem errar. Não é mapeamento de processo.
A5: COMO PREENCHER: as linhas em azul-claro já vêm preenchidas com o que a plataforma de dados hoje sabe deste setor — sua tarefa é CONFIRMAR ou CORRIGIR, e acrescentar o que falta nas linhas em branco. Se discordar de uma linha pré-preenchida, sobrescreva: a sua versão vale mais que a minha.
A7: FICHA DO SETOR
A8: Quem responde por este preenchimento
A9: Cargo / função
A10: Sistemas que o setor usa no dia a dia
A11: Com que frequência o setor decide com dado
A12: Período que costuma olhar (ex.: mês corrente, últimos 90 dias)
A14: 1. PERGUNTAS QUE O SETOR PRECISA RESPONDER COM DADO — define o que a camada Refined tem de servir
A15: Pergunta | B15: Decisão que depende dela | C15: Frequência | D15: Hoje consegue responder? | E15: Onde busca hoje | G15: Origem da linha
A16: Onde o mesmo termo significa coisas diferentes entre setores? | B16: Padronização do vocabulário da casa | C16: Trimestral | E16: este próprio levantamento | G16: pré-preenchido — confirme ou corrija
A17: Que perguntas de negócio nenhum setor consegue responder hoje? | B17: Priorização do roadmap de dados | C17: Trimestral | E17: coluna 'Hoje consegue responder?' das outras abas | G17: pré-preenchido — confirme ou corrija
A30: 2. INDICADORES — nome, cálculo e, sobretudo, o que NÃO vale fazer com ele
A31: Indicador | B31: Como se calcula (em palavras) | C31: Unidade | D31: Recorte habitual | E31: O que NÃO vale fazer com ele | F31: Dono da definição | G31: Origem da linha
A32: Perguntas sem resposta | B32: Contar perguntas marcadas 'Não' em todas as abas | C32: un. | D32: Setor | E32: Não é indicador de desempenho de setor — é fila de trabalho da plataforma de dados. | G32: pré-preenchido — confirme ou corrija
A51: 3. VOCABULÁRIO DO SETOR — o bloco mais barato e o de maior retorno
A52: Termo | B52: O que significa NESTE setor | E52: Onde aparece no dado | G52: Origem da linha
A53: Camada semântica | B53: Documentação que diz o que o número significa e como lê-lo sem errar | E53: Nekt — documentos de contexto | G53: pré-preenchido — confirme ou corrija
A54: Refined | B54: Camada oficial de consumo, onde moram as regras de negócio | E54: prefixo rfn_ | G54: pré-preenchido — confirme ou corrija

Sheet Consolidado
A1: Consolidado do Levantamento Semântico
A2: VAN-SEM-001 | Versão 1.0 | Emissão 11/09/2026
A4: ESTA ABA É TODA CALCULADA — não digite nada aqui. 'Situação' fica Pronto quando o setor tem a ficha completa, ao menos 2 perguntas, 3 indicadores e 3 termos. A coluna 'Sem resposta hoje' é a fila de trabalho da plataforma: são perguntas de negócio que o dado ainda não responde.
A6: Setor | B6: Ficha (de 5) | C6: Perguntas | D6: Sem resposta hoje | E6: Indicadores | F6: Com regra de 'não vale' | G6: Termos | H6: Situação
A7: Mídia Paga | B7: =COUNTIF('Mídia Paga'!$B$8:$B$12,"?*") | C7: =COUNTIF('Mídia Paga'!$A$16:$A$28,"?*") | D7: =COUNTIF('Mídia Paga'!$D$16:$D$28,"Não") | E7: =COUNTIF('Mídia Paga'!$A$32:$A$49,"?*") | F7: =COUNTIF('Mídia Paga'!$E$32:$E$49,"?*") | G7: =COUNTIF('Mídia Paga'!$A$53:$A$65,"?*") | H7: =IF(AND($B7=5,$C7>=2,$E7>=3,$G7>=3),"Pronto","Falta preencher")
A8: Inbound | B8: =COUNTIF('Inbound'!$B$8:$B$12,"?*") | C8: =COUNTIF('Inbound'!$A$16:$A$28,"?*") | D8: =COUNTIF('Inbound'!$D$16:$D$28,"Não") | E8: =COUNTIF('Inbound'!$A$32:$A$49,"?*") | F8: =COUNTIF('Inbound'!$E$32:$E$49,"?*") | G8: =COUNTIF('Inbound'!$A$53:$A$65,"?*") | H8: =IF(AND($B8=5,$C8>=2,$E8>=3,$G8>=3),"Pronto","Falta preencher")
A9: Account (Atendimento) | B9: =COUNTIF('Account'!$B$8:$B$12,"?*") | C9: =COUNTIF('Account'!$A$16:$A$28,"?*") | D9: =COUNTIF('Account'!$D$16:$D$28,"Não") | E9: =COUNTIF('Account'!$A$32:$A$49,"?*") | F9: =COUNTIF('Account'!$E$32:$E$49,"?*") | G9: =COUNTIF('Account'!$A$53:$A$65,"?*") | H9: =IF(AND($B9=5,$C9>=2,$E9>=3,$G9>=3),"Pronto","Falta preencher")
A10: Criação | B10: =COUNTIF('Criação'!$B$8:$B$12,"?*") | C10: =COUNTIF('Criação'!$A$16:$A$28,"?*") | D10: =COUNTIF('Criação'!$D$16:$D$28,"Não") | E10: =COUNTIF('Criação'!$A$32:$A$49,"?*") | F10: =COUNTIF('Criação'!$E$32:$E$49,"?*") | G10: =COUNTIF('Criação'!$A$53:$A$65,"?*") | H10: =IF(AND($B10=5,$C10>=2,$E10>=3,$G10>=3),"Pronto","Falta preencher")
A11: Direção de Arte | B11: =COUNTIF('Direção de Arte'!$B$8:$B$12,"?*") | C11: =COUNTIF('Direção de Arte'!$A$16:$A$28,"?*") | D11: =COUNTIF('Direção de Arte'!$D$16:$D$28,"Não") | E11: =COUNTIF('Direção de Arte'!$A$32:$A$49,"?*") | F11: =COUNTIF('Direção de Arte'!$E$32:$E$49,"?*") | G11: =COUNTIF('Direção de Arte'!$A$53:$A$65,"?*") | H11: =IF(AND($B11=5,$C11>=2,$E11>=3,$G11>=3),"Pronto","Falta preencher")
A12: Diretoria de Operações | B12: =COUNTIF('Dir. Operações'!$B$8:$B$12,"?*") | C12: =COUNTIF('Dir. Operações'!$A$16:$A$28,"?*") | D12: =COUNTIF('Dir. Operações'!$D$16:$D$28,"Não") | E12: =COUNTIF('Dir. Operações'!$A$32:$A$49,"?*") | F12: =COUNTIF('Dir. Operações'!$E$32:$E$49,"?*") | G12: =COUNTIF('Dir. Operações'!$A$53:$A$65,"?*") | H12: =IF(AND($B12=5,$C12>=2,$E12>=3,$G12>=3),"Pronto","Falta preencher")
A13: Recursos Humanos | B13: =COUNTIF('RH'!$B$8:$B$12,"?*") | C13: =COUNTIF('RH'!$A$16:$A$28,"?*") | D13: =COUNTIF('RH'!$D$16:$D$28,"Não") | E13: =COUNTIF('RH'!$A$32:$A$49,"?*") | F13: =COUNTIF('RH'!$E$32:$E$49,"?*") | G13: =COUNTIF('RH'!$A$53:$A$65,"?*") | H13: =IF(AND($B13=5,$C13>=2,$E13>=3,$G13>=3),"Pronto","Falta preencher")
A14: Diretoria Executiva | B14: =COUNTIF('Dir. Executiva'!$B$8:$B$12,"?*") | C14: =COUNTIF('Dir. Executiva'!$A$16:$A$28,"?*") | D14: =COUNTIF('Dir. Executiva'!$D$16:$D$28,"Não") | E14: =COUNTIF('Dir. Executiva'!$A$32:$A$49,"?*") | F14: =COUNTIF('Dir. Executiva'!$E$32:$E$49,"?*") | G14: =COUNTIF('Dir. Executiva'!$A$53:$A$65,"?*") | H14: =IF(AND($B14=5,$C14>=2,$E14>=3,$G14>=3),"Pronto","Falta preencher")
A15: Social Media | B15: =COUNTIF('Social Media'!$B$8:$B$12,"?*") | C15: =COUNTIF('Social Media'!$A$16:$A$28,"?*") | D15: =COUNTIF('Social Media'!$D$16:$D$28,"Não") | E15: =COUNTIF('Social Media'!$A$32:$A$49,"?*") | F15: =COUNTIF('Social Media'!$E$32:$E$49,"?*") | G15: =COUNTIF('Social Media'!$A$53:$A$65,"?*") | H15: =IF(AND($B15=5,$C15>=2,$E15>=3,$G15>=3),"Pronto","Falta preencher")
A16: Financeiro / Controladoria | B16: =COUNTIF('Financeiro'!$B$8:$B$12,"?*") | C16: =COUNTIF('Financeiro'!$A$16:$A$28,"?*") | D16: =COUNTIF('Financeiro'!$D$16:$D$28,"Não") | E16: =COUNTIF('Financeiro'!$A$32:$A$49,"?*") | F16: =COUNTIF('Financeiro'!$E$32:$E$49,"?*") | G16: =COUNTIF('Financeiro'!$A$53:$A$65,"?*") | H16: =IF(AND($B16=5,$C16>=2,$E16>=3,$G16>=3),"Pronto","Falta preencher")
A17: Planejamento, Estratégia e Inovação | B17: =COUNTIF('Planej. Estrat. e Inovação'!$B$8:$B$12,"?*") | C17: =COUNTIF('Planej. Estrat. e Inovação'!$A$16:$A$28,"?*") | D17: =COUNTIF('Planej. Estrat. e Inovação'!$D$16:$D$28,"Não") | E17: =COUNTIF('Planej. Estrat. e Inovação'!$A$32:$A$49,"?*") | F17: =COUNTIF('Planej. Estrat. e Inovação'!$E$32:$E$49,"?*") | G17: =COUNTIF('Planej. Estrat. e Inovação'!$A$53:$A$65,"?*") | H17: =IF(AND($B17=5,$C17>=2,$E17>=3,$G17>=3),"Pronto","Falta preencher")
A18: TOTAL | B18: =SUM(B7:B17) | C18: =SUM(C7:C17) | D18: =SUM(D7:D17) | E18: =SUM(E7:E17) | F18: =SUM(F7:F17) | G18: =SUM(G7:G17) | H18: =COUNTIF($H$7:$H17,"Pronto")&" de 11 setores"
